[
  {
    "id": 111708807,
    "createdAt": "2021-10-18T09:17:40.000Z",
    "updatedAt": null,
    "key": "$PSP_GAME\\USRDIR\\St000\\St004_Cp2101.bin_0",
    "original": "「う～っ、緊張してきた」",
    "translation": "",
    "file": 386041,
    "stage": 0,
    "project": 3318,
    "uid": null,
    "extra": null,
    "context": "伊織",
    "words": 1
  },
  {
    "id": 111708808,
    "createdAt": "2021-10-18T09:17:40.000Z",
    "updatedAt": null,
    "key": "$PSP_GAME\\USRDIR\\St000\\St004_Cp2101.bin_1",
    "original": "（稲葉んと仲直りできたことで、\\n　自分の心にも少し余裕が出来たかな。\\n　……今なら、稲葉んの恋を全力で応援できる気がするよ）",
    "translation": "",
    "file": 386041,
    "stage": 0,
    "project": 3318,
    "uid": null,
    "extra": null,
    "context": "",
    "words": 3
  },
  {
    "id": 111708809,
    "createdAt": "2021-10-18T09:17:40.000Z",
    "updatedAt": null,
    "key": "$PSP_GAME\\USRDIR\\St000\\St004_Cp2101.bin_2",
    "original": "（だから、見届けなきゃ、稲葉んの告白……）",
    "translation": "",
    "file": 386041,
    "stage": 0,
    "project": 3318,
    "uid": null,
    "extra": null,
    "context": "",
    "words": 1
  },
  {
    "id": 111708810,
    "createdAt": "2021-10-18T09:17:40.000Z",
    "updatedAt": null,
    "key": "$PSP_GAME\\USRDIR\\St000\\St004_Cp2101.bin_3",
    "original": "（太一はもうあそこに来てる。\\n　で、稲葉んは……）",
    "translation": "",
    "file": 386041,
    "stage": 0,
    "project": 3318,
    "uid": null,
    "extra": null,
    "context": "",
    "words": 2
  },
  {
    "id": 111708811,
    "createdAt": "2021-10-18T09:17:40.000Z",
    "updatedAt": null,
    "key": "$PSP_GAME\\USRDIR\\St000\\St004_Cp2101.bin_4",
    "original": "「あれ、稲葉ん、まだ来てない。\\n　一体どこに……」",
    "translation": "",
    "file": 386041,
    "stage": 0,
    "project": 3318,
    "uid": null,
    "extra": null,
    "context": "",
    "words": 2
  },
  {
    "id": 111708812,
    "createdAt": "2021-10-18T09:17:40.000Z",
    "updatedAt": null,
    "key": "$PSP_GAME\\USRDIR\\St000\\St004_Cp2101.bin_5",
    "original": "「……こ、ここだ」",
    "translation": "",
    "file": 386041,
    "stage": 0,
    "project": 3318,
    "uid": null,
    "extra": null,
    "context": "稲葉",
    "words": 1
  },
  {
    "id": 111708813,
    "createdAt": "2021-10-18T09:17:40.000Z",
    "updatedAt": null,
    "key": "$PSP_GAME\\USRDIR\\St000\\St004_Cp2101.bin_6",
    "original": "「ひゃうっっ！？\\n　な、なにしてるのさ稲葉ん。早く行かなきゃ！」",
    "translation": "",
    "file": 386041,
    "stage": 0,
    "project": 3318,
    "uid": null,
    "extra": null,
    "context": "伊織",
    "words": 2
  },
  {
    "id": 111708814,
    "createdAt": "2021-10-18T09:17:40.000Z",
    "updatedAt": null,
    "key": "$PSP_GAME\\USRDIR\\St000\\St004_Cp2101.bin_7",
    "original": "「わ、わかってる……」",
    "translation": "",
    "file": 386041,
    "stage": 0,
    "project": 3318,
    "uid": null,
    "extra": null,
    "context": "稲葉",
    "words": 1
  },
  {
    "id": 111708815,
    "createdAt": "2021-10-18T09:17:40.000Z",
    "updatedAt": null,
    "key": "$PSP_GAME\\USRDIR\\St000\\St004_Cp2101.bin_8",
    "original": "「うん、全力で行ってこいっ！」",
    "translation": "",
    "file": 386041,
    "stage": 0,
    "project": 3318,
    "uid": null,
    "extra": null,
    "context": "伊織",
    "words": 1
  },
  {
    "id": 111708816,
    "createdAt": "2021-10-18T09:17:40.000Z",
    "updatedAt": null,
    "key": "$PSP_GAME\\USRDIR\\St000\\St004_Cp2101.bin_9",
    "original": "「よしっ。…行ってくる！」",
    "translation": "",
    "file": 386041,
    "stage": 0,
    "project": 3318,
    "uid": null,
    "extra": null,
    "context": "稲葉",
    "words": 1
  },
  {
    "id": 111708817,
    "createdAt": "2021-10-18T09:17:40.000Z",
    "updatedAt": null,
    "key": "$PSP_GAME\\USRDIR\\St000\\St004_Cp2101.bin_10",
    "original": "「…………」",
    "translation": "",
    "file": 386041,
    "stage": 0,
    "project": 3318,
    "uid": null,
    "extra": null,
    "context": "",
    "words": 1
  },
  {
    "id": 111708818,
    "createdAt": "2021-10-18T09:17:40.000Z",
    "updatedAt": null,
    "key": "$PSP_GAME\\USRDIR\\St000\\St004_Cp2101.bin_11",
    "original": "「待たせたな……太一」",
    "translation": "",
    "file": 386041,
    "stage": 0,
    "project": 3318,
    "uid": null,
    "extra": null,
    "context": "",
    "words": 1
  },
  {
    "id": 111708819,
    "createdAt": "2021-10-18T09:17:40.000Z",
    "updatedAt": null,
    "key": "$PSP_GAME\\USRDIR\\St000\\St004_Cp2101.bin_12",
    "original": "「あ、ああ……それで稲葉、用事っていうのは？」",
    "translation": "",
    "file": 386041,
    "stage": 0,
    "project": 3318,
    "uid": null,
    "extra": null,
    "context": "太一",
    "words": 1
  },
  {
    "id": 111708820,
    "createdAt": "2021-10-18T09:17:40.000Z",
    "updatedAt": null,
    "key": "$PSP_GAME\\USRDIR\\St000\\St004_Cp2101.bin_13",
    "original": "「ああ、\\n　えーその……太一と伊織はさ。\\n　今、微妙な感じ……だよな」",
    "translation": "",
    "file": 386041,
    "stage": 0,
    "project": 3318,
    "uid": null,
    "extra": null,
    "context": "稲葉",
    "words": 3
  },
  {
    "id": 111708821,
    "createdAt": "2021-10-18T09:17:40.000Z",
    "updatedAt": null,
    "key": "$PSP_GAME\\USRDIR\\St000\\St004_Cp2101.bin_14",
    "original": "「……ああ」",
    "translation": "",
    "file": 386041,
    "stage": 0,
    "project": 3318,
    "uid": null,
    "extra": null,
    "context": "太一",
    "words": 1
  },
  {
    "id": 111708822,
    "createdAt": "2021-10-18T09:17:40.000Z",
    "updatedAt": null,
    "key": "$PSP_GAME\\USRDIR\\St000\\St004_Cp2101.bin_15",
    "original": "「あー、落ち込むなっ。そうじゃねえんだっ。\\n　掘り返そうとした訳じゃない！」",
    "translation": "",
    "file": 386041,
    "stage": 0,
    "project": 3318,
    "uid": null,
    "extra": null,
    "context": "稲葉",
    "words": 2
  },
  {
    "id": 111708823,
    "createdAt": "2021-10-18T09:17:40.000Z",
    "updatedAt": null,
    "key": "$PSP_GAME\\USRDIR\\St000\\St004_Cp2101.bin_16",
    "original": "「弱みにつけ込もうとしてるんじゃないってことを\\n　はっきり言っておきたいんだ。\\n　それを最初に言っておきたかった」",
    "translation": "",
    "file": 386041,
    "stage": 0,
    "project": 3318,
    "uid": null,
    "extra": null,
    "context": "",
    "words": 3
  },
  {
    "id": 111708824,
    "createdAt": "2021-10-18T09:17:40.000Z",
    "updatedAt": null,
    "key": "$PSP_GAME\\USRDIR\\St000\\St004_Cp2101.bin_17",
    "original": "（稲葉ん……）",
    "translation": "",
    "file": 386041,
    "stage": 0,
    "project": 3318,
    "uid": null,
    "extra": null,
    "context": "伊織",
    "words": 1
  },
  {
    "id": 111708825,
    "createdAt": "2021-10-18T09:17:40.000Z",
    "updatedAt": null,
    "key": "$PSP_GAME\\USRDIR\\St000\\St004_Cp2101.bin_18",
    "original": "（稲葉んは……立派だ。\\n　堂々と自分の気持ちと向かい合っている）",
    "translation": "",
    "file": 386041,
    "stage": 0,
    "project": 3318,
    "uid": null,
    "extra": null,
    "context": "",
    "words": 2
  },
  {
    "id": 111708826,
    "createdAt": "2021-10-18T09:17:40.000Z",
    "updatedAt": null,
    "key": "$PSP_GAME\\USRDIR\\St000\\St004_Cp2101.bin_19",
    "original": "（いろんなことがあったけど、そんなの関係なく、\\n　真っ直ぐに自分の気持ちを見つめてる）",
    "translation": "",
    "file": 386041,
    "stage": 0,
    "project": 3318,
    "uid": null,
    "extra": null,
    "context": "",
    "words": 2
  },
  {
    "id": 111708827,
    "createdAt": "2021-10-18T09:17:40.000Z",
    "updatedAt": null,
    "key": "$PSP_GAME\\USRDIR\\St000\\St004_Cp2101.bin_20",
    "original": "「アタシさ……。どうしても言わなきゃならないことが\\n　あるんだよ、太一に」",
    "translation": "",
    "file": 386041,
    "stage": 0,
    "project": 3318,
    "uid": null,
    "extra": null,
    "context": "稲葉",
    "words": 2
  },
  {
    "id": 111708828,
    "createdAt": "2021-10-18T09:17:40.000Z",
    "updatedAt": null,
    "key": "$PSP_GAME\\USRDIR\\St000\\St004_Cp2101.bin_21",
    "original": "「俺に……？」",
    "translation": "",
    "file": 386041,
    "stage": 0,
    "project": 3318,
    "uid": null,
    "extra": null,
    "context": "太一",
    "words": 1
  },
  {
    "id": 111708829,
    "createdAt": "2021-10-18T09:17:40.000Z",
    "updatedAt": null,
    "key": "$PSP_GAME\\USRDIR\\St000\\St004_Cp2101.bin_22",
    "original": "「……。太一、あのさ……」",
    "translation": "",
    "file": 386041,
    "stage": 0,
    "project": 3318,
    "uid": null,
    "extra": null,
    "context": "稲葉",
    "words": 1
  },
  {
    "id": 111708830,
    "createdAt": "2021-10-18T09:17:40.000Z",
    "updatedAt": null,
    "key": "$PSP_GAME\\USRDIR\\St000\\St004_Cp2101.bin_23",
    "original": "「あ、あ、アタシは……！」",
    "translation": "",
    "file": 386041,
    "stage": 0,
    "project": 3318,
    "uid": null,
    "extra": null,
    "context": "",
    "words": 1
  },
  {
    "id": 111708831,
    "createdAt": "2021-10-18T09:17:40.000Z",
    "updatedAt": null,
    "key": "$PSP_GAME\\USRDIR\\St000\\St004_Cp2101.bin_24",
    "original": "「……好きだ」",
    "translation": "",
    "file": 386041,
    "stage": 0,
    "project": 3318,
    "uid": null,
    "extra": null,
    "context": "",
    "words": 1
  },
  {
    "id": 111708832,
    "createdAt": "2021-10-18T09:17:40.000Z",
    "updatedAt": null,
    "key": "$PSP_GAME\\USRDIR\\St000\\St004_Cp2101.bin_25",
    "original": "（言ったー！！　すごいよ稲葉ん！！）",
    "translation": "",
    "file": 386041,
    "stage": 0,
    "project": 3318,
    "uid": null,
    "extra": null,
    "context": "伊織",
    "words": 2
  },
  {
    "id": 111708833,
    "createdAt": "2021-10-18T09:17:40.000Z",
    "updatedAt": null,
    "key": "$PSP_GAME\\USRDIR\\St000\\St004_Cp2101.bin_26",
    "original": "「……え？　ええええ！？」",
    "translation": "",
    "file": 386041,
    "stage": 0,
    "project": 3318,
    "uid": null,
    "extra": null,
    "context": "太一",
    "words": 2
  },
  {
    "id": 111708834,
    "createdAt": "2021-10-18T09:17:40.000Z",
    "updatedAt": null,
    "key": "$PSP_GAME\\USRDIR\\St000\\St004_Cp2101.bin_27",
    "original": "「お、驚く気持ちもわかる。\\n　だが、本当だ。お前が好きなんだ」",
    "translation": "",
    "file": 386041,
    "stage": 0,
    "project": 3318,
    "uid": null,
    "extra": null,
    "context": "稲葉",
    "words": 2
  },
  {
    "id": 111708835,
    "createdAt": "2021-10-18T09:17:40.000Z",
    "updatedAt": null,
    "key": "$PSP_GAME\\USRDIR\\St000\\St004_Cp2101.bin_28",
    "original": "「……稲葉……かなり驚いたが、気持ちは嬉しい」",
    "translation": "",
    "file": 386041,
    "stage": 0,
    "project": 3318,
    "uid": null,
    "extra": null,
    "context": "太一",
    "words": 1
  },
  {
    "id": 111708836,
    "createdAt": "2021-10-18T09:17:40.000Z",
    "updatedAt": null,
    "key": "$PSP_GAME\\USRDIR\\St000\\St004_Cp2101.bin_29",
    "original": "「よし！　伝えたぞ。伝えたからな。\\n　ああ、返事は今しなくても良い。\\n　じっくり考えて返答してくれ、それじゃっ！！」",
    "translation": "",
    "file": 386041,
    "stage": 0,
    "project": 3318,
    "uid": null,
    "extra": null,
    "context": "稲葉",
    "words": 4
  },
  {
    "id": 111708837,
    "createdAt": "2021-10-18T09:17:40.000Z",
    "updatedAt": null,
    "key": "$PSP_GAME\\USRDIR\\St000\\St004_Cp2101.bin_30",
    "original": "「稲葉……」",
    "translation": "",
    "file": 386041,
    "stage": 0,
    "project": 3318,
    "uid": null,
    "extra": null,
    "context": "太一",
    "words": 1
  },
  {
    "id": 111708838,
    "createdAt": "2021-10-18T09:17:40.000Z",
    "updatedAt": null,
    "key": "$PSP_GAME\\USRDIR\\St000\\St004_Cp2101.bin_31",
    "original": "「ここに居てもしょうがない。俺も行くか……」",
    "translation": "",
    "file": 386041,
    "stage": 0,
    "project": 3318,
    "uid": null,
    "extra": null,
    "context": "",
    "words": 1
  },
  {
    "id": 111708839,
    "createdAt": "2021-10-18T09:17:40.000Z",
    "updatedAt": null,
    "key": "$PSP_GAME\\USRDIR\\St000\\St004_Cp2101.bin_32",
    "original": "「稲葉ん、ちゃんと太一に気持ちを伝えた。\\n　真っ直ぐに。逃げずに……」",
    "translation": "",
    "file": 386041,
    "stage": 0,
    "project": 3318,
    "uid": null,
    "extra": null,
    "context": "伊織",
    "words": 2
  },
  {
    "id": 111708840,
    "createdAt": "2021-10-18T09:17:40.000Z",
    "updatedAt": null,
    "key": "$PSP_GAME\\USRDIR\\St000\\St004_Cp2101.bin_33",
    "original": "（これで……ぜんぶ丸く収まるかな……）",
    "translation": "",
    "file": 386041,
    "stage": 0,
    "project": 3318,
    "uid": null,
    "extra": null,
    "context": "",
    "words": 1
  },
  {
    "id": 111708841,
    "createdAt": "2021-10-18T09:17:40.000Z",
    "updatedAt": null,
    "key": "$PSP_GAME\\USRDIR\\St000\\St004_Cp2101.bin_34",
    "original": "「おめでとう、稲葉ん」",
    "translation": "",
    "file": 386041,
    "stage": 0,
    "project": 3318,
    "uid": null,
    "extra": null,
    "context": "Choice",
    "words": 1
  },
  {
    "id": 111708842,
    "createdAt": "2021-10-18T09:17:40.000Z",
    "updatedAt": null,
    "key": "$PSP_GAME\\USRDIR\\St000\\St004_Cp2101.bin_35",
    "original": "「…………」",
    "translation": "",
    "file": 386041,
    "stage": 0,
    "project": 3318,
    "uid": null,
    "extra": null,
    "context": "",
    "words": 1
  },
  {
    "id": 111708843,
    "createdAt": "2021-10-18T09:17:40.000Z",
    "updatedAt": null,
    "key": "$PSP_GAME\\USRDIR\\St000\\St004_Cp2101.bin_36",
    "original": "「おめでとう、稲葉ん」",
    "translation": "",
    "file": 386041,
    "stage": 0,
    "project": 3318,
    "uid": null,
    "extra": null,
    "context": "伊織",
    "words": 1
  },
  {
    "id": 111708844,
    "createdAt": "2021-10-18T09:17:40.000Z",
    "updatedAt": null,
    "key": "$PSP_GAME\\USRDIR\\St000\\St004_Cp2101.bin_37",
    "original": "（何でだろ？　親友の晴れ舞台を見届けたのに、\\n　心からおめでとうって思ったはずなのに……)",
    "translation": "",
    "file": 386041,
    "stage": 0,
    "project": 3318,
    "uid": null,
    "extra": null,
    "context": "",
    "words": 3
  },
  {
    "id": 111708845,
    "createdAt": "2021-10-18T09:17:40.000Z",
    "updatedAt": null,
    "key": "$PSP_GAME\\USRDIR\\St000\\St004_Cp2101.bin_38",
    "original": "（わたし、よろこんでない……？\\n　全然よろこべてない……）",
    "translation": "",
    "file": 386041,
    "stage": 0,
    "project": 3318,
    "uid": null,
    "extra": null,
    "context": "",
    "words": 2
  },
  {
    "id": 111708846,
    "createdAt": "2021-10-18T09:17:40.000Z",
    "updatedAt": null,
    "key": "$PSP_GAME\\USRDIR\\St000\\St004_Cp2101.bin_39",
    "original": "「…………」",
    "translation": "",
    "file": 386041,
    "stage": 0,
    "project": 3318,
    "uid": null,
    "extra": null,
    "context": "",
    "words": 1
  },
  {
    "id": 111708847,
    "createdAt": "2021-10-18T09:17:40.000Z",
    "updatedAt": null,
    "key": "$PSP_GAME\\USRDIR\\St000\\St004_Cp2101.bin_40",
    "original": "（おめでとう稲葉んって、言うつもりだったのに。\\n　でも、口がまったく動かない……）",
    "translation": "",
    "file": 386041,
    "stage": 0,
    "project": 3318,
    "uid": null,
    "extra": null,
    "context": "",
    "words": 2
  },
  {
    "id": 111708848,
    "createdAt": "2021-10-18T09:17:40.000Z",
    "updatedAt": null,
    "key": "$PSP_GAME\\USRDIR\\St000\\St004_Cp2101.bin_41",
    "original": "（なんだか、胸が苦しい）",
    "translation": "",
    "file": 386041,
    "stage": 0,
    "project": 3318,
    "uid": null,
    "extra": null,
    "context": "",
    "words": 1
  },
  {
    "id": 111708849,
    "createdAt": "2021-10-18T09:17:40.000Z",
    "updatedAt": null,
    "key": "$PSP_GAME\\USRDIR\\St000\\St004_Cp2101.bin_42",
    "original": "（稲葉んは親友……。\\n　親友だけど、でも……）",
    "translation": "",
    "file": 386041,
    "stage": 0,
    "project": 3318,
    "uid": null,
    "extra": null,
    "context": "",
    "words": 2
  },
  {
    "id": 111708850,
    "createdAt": "2021-10-18T09:17:40.000Z",
    "updatedAt": null,
    "key": "$PSP_GAME\\USRDIR\\St000\\St004_Cp2101.bin_43",
    "original": "（わたしと稲葉んの絆は崩れない。\\n　わたしは今、どうしたいんだろう）",
    "translation": "",
    "file": 386041,
    "stage": 0,
    "project": 3318,
    "uid": null,
    "extra": null,
    "context": "",
    "words": 2
  },
  {
    "id": 111708851,
    "createdAt": "2021-10-18T09:17:40.000Z",
    "updatedAt": null,
    "key": "$PSP_GAME\\USRDIR\\St000\\St004_Cp2101.bin_44",
    "original": "（わたしの気持ちは、太一への想いは、\\n　まだ残っている……\\n　私が本当にしたいことは……）",
    "translation": "",
    "file": 386041,
    "stage": 0,
    "project": 3318,
    "uid": null,
    "extra": null,
    "context": "",
    "words": 3
  }
]