[
  {
    "id": 111710413,
    "createdAt": "2021-10-18T09:17:56.000Z",
    "updatedAt": "2021-11-14T11:21:11.000Z",
    "key": "$PSP_GAME\\USRDIR\\St000\\St006_Cp0501.bin_0",
    "original": "放課後",
    "translation": "放学后",
    "file": 386081,
    "stage": 3,
    "project": 3318,
    "uid": 24520,
    "extra": null,
    "context": "Time",
    "words": 1
  },
  {
    "id": 111710414,
    "createdAt": "2021-10-18T09:17:56.000Z",
    "updatedAt": "2021-11-14T11:21:13.000Z",
    "key": "$PSP_GAME\\USRDIR\\St000\\St006_Cp0501.bin_1",
    "original": "通学路",
    "translation": "放学路上",
    "file": 386081,
    "stage": 3,
    "project": 3318,
    "uid": 24520,
    "extra": null,
    "context": "Location",
    "words": 1
  },
  {
    "id": 111710415,
    "createdAt": "2021-10-18T09:17:56.000Z",
    "updatedAt": "2021-11-14T10:50:24.000Z",
    "key": "$PSP_GAME\\USRDIR\\St000\\St006_Cp0501.bin_2",
    "original": "「…………」",
    "translation": "「…………」",
    "file": 386081,
    "stage": 3,
    "project": 3318,
    "uid": 24520,
    "extra": null,
    "context": "大沢",
    "words": 1
  },
  {
    "id": 111710416,
    "createdAt": "2021-10-18T09:17:56.000Z",
    "updatedAt": "2021-11-14T10:50:25.000Z",
    "key": "$PSP_GAME\\USRDIR\\St000\\St006_Cp0501.bin_3",
    "original": "「――――」",
    "translation": "「――――」",
    "file": 386081,
    "stage": 3,
    "project": 3318,
    "uid": 24520,
    "extra": null,
    "context": "唯",
    "words": 1
  },
  {
    "id": 111710417,
    "createdAt": "2021-10-18T09:17:56.000Z",
    "updatedAt": "2021-11-14T10:50:48.000Z",
    "key": "$PSP_GAME\\USRDIR\\St000\\St006_Cp0501.bin_4",
    "original": "「ちょっと…強引だったかな…？」",
    "translation": "「是不是有点…勉强你了啊…？」",
    "file": 386081,
    "stage": 3,
    "project": 3318,
    "uid": 24520,
    "extra": null,
    "context": "大沢",
    "words": 1
  },
  {
    "id": 111710418,
    "createdAt": "2021-10-18T09:17:56.000Z",
    "updatedAt": "2021-11-14T10:51:26.000Z",
    "key": "$PSP_GAME\\USRDIR\\St000\\St006_Cp0501.bin_5",
    "original": "「いえ！」",
    "translation": "「没有！」",
    "file": 386081,
    "stage": 3,
    "project": 3318,
    "uid": 24520,
    "extra": null,
    "context": "唯",
    "words": 1
  },
  {
    "id": 111710419,
    "createdAt": "2021-10-18T09:17:56.000Z",
    "updatedAt": "2021-11-14T10:51:28.000Z",
    "key": "$PSP_GAME\\USRDIR\\St000\\St006_Cp0501.bin_6",
    "original": "「そんな事…ないです…」",
    "translation": "「没有…那事…」",
    "file": 386081,
    "stage": 3,
    "project": 3318,
    "uid": 24520,
    "extra": null,
    "context": "",
    "words": 1
  },
  {
    "id": 111710420,
    "createdAt": "2021-10-18T09:17:56.000Z",
    "updatedAt": "2021-11-14T10:51:29.000Z",
    "key": "$PSP_GAME\\USRDIR\\St000\\St006_Cp0501.bin_7",
    "original": "「なんで敬語？」",
    "translation": "「为什么用敬语？」",
    "file": 386081,
    "stage": 3,
    "project": 3318,
    "uid": 24520,
    "extra": null,
    "context": "大沢",
    "words": 1
  },
  {
    "id": 111710421,
    "createdAt": "2021-10-18T09:17:56.000Z",
    "updatedAt": "2021-11-14T10:51:31.000Z",
    "key": "$PSP_GAME\\USRDIR\\St000\\St006_Cp0501.bin_8",
    "original": "「ええ！？　だって！」",
    "translation": "「诶诶！？因为！」",
    "file": 386081,
    "stage": 3,
    "project": 3318,
    "uid": 24520,
    "extra": null,
    "context": "唯",
    "words": 2
  },
  {
    "id": 111710422,
    "createdAt": "2021-10-18T09:17:56.000Z",
    "updatedAt": "2021-11-14T10:51:43.000Z",
    "key": "$PSP_GAME\\USRDIR\\St000\\St006_Cp0501.bin_9",
    "original": "「あたし…大沢さんの事…まだ…よく知らないし…\\n　そもそも…名前だって…今日初めて…」",
    "translation": "「我…对于大沢同学…还…不太了解…\\n　连…名字都是…今天第一次…」",
    "file": 386081,
    "stage": 3,
    "project": 3318,
    "uid": 24520,
    "extra": null,
    "context": "",
    "words": 2
  },
  {
    "id": 111710423,
    "createdAt": "2021-10-18T09:17:56.000Z",
    "updatedAt": "2021-11-14T10:51:45.000Z",
    "key": "$PSP_GAME\\USRDIR\\St000\\St006_Cp0501.bin_10",
    "original": "「なら、まず敬語をやめない？　ね？」",
    "translation": "「那就，首先别用敬语了吧？　呐？」",
    "file": 386081,
    "stage": 3,
    "project": 3318,
    "uid": 24520,
    "extra": null,
    "context": "大沢",
    "words": 2
  },
  {
    "id": 111710424,
    "createdAt": "2021-10-18T09:17:56.000Z",
    "updatedAt": "2021-11-14T10:51:46.000Z",
    "key": "$PSP_GAME\\USRDIR\\St000\\St006_Cp0501.bin_11",
    "original": "「は…はい…わかりました…」",
    "translation": "「额…嗯…知道了…」",
    "file": 386081,
    "stage": 3,
    "project": 3318,
    "uid": 24520,
    "extra": null,
    "context": "唯",
    "words": 1
  },
  {
    "id": 111710425,
    "createdAt": "2021-10-18T09:17:56.000Z",
    "updatedAt": "2021-11-14T10:51:49.000Z",
    "key": "$PSP_GAME\\USRDIR\\St000\\St006_Cp0501.bin_12",
    "original": "「ぷ…！」",
    "translation": "「噗…！」",
    "file": 386081,
    "stage": 3,
    "project": 3318,
    "uid": 24520,
    "extra": null,
    "context": "大沢",
    "words": 1
  },
  {
    "id": 111710426,
    "createdAt": "2021-10-18T09:17:56.000Z",
    "updatedAt": "2021-11-14T10:51:50.000Z",
    "key": "$PSP_GAME\\USRDIR\\St000\\St006_Cp0501.bin_13",
    "original": "「あ！」",
    "translation": "「啊！」",
    "file": 386081,
    "stage": 3,
    "project": 3318,
    "uid": 24520,
    "extra": null,
    "context": "唯",
    "words": 1
  },
  {
    "id": 111710427,
    "createdAt": "2021-10-18T09:17:56.000Z",
    "updatedAt": "2021-11-14T10:51:51.000Z",
    "key": "$PSP_GAME\\USRDIR\\St000\\St006_Cp0501.bin_14",
    "original": "「あははは！　わたしってそんなに威圧感ある？」",
    "translation": "「啊哈哈哈！ 我就那么有威压感吗？」",
    "file": 386081,
    "stage": 3,
    "project": 3318,
    "uid": 24520,
    "extra": null,
    "context": "大沢",
    "words": 2
  },
  {
    "id": 111710428,
    "createdAt": "2021-10-18T09:17:56.000Z",
    "updatedAt": "2021-11-14T10:51:52.000Z",
    "key": "$PSP_GAME\\USRDIR\\St000\\St006_Cp0501.bin_15",
    "original": "「いえいえ！　全然！」",
    "translation": "「没没！完全没！」",
    "file": 386081,
    "stage": 3,
    "project": 3318,
    "uid": 24520,
    "extra": null,
    "context": "唯",
    "words": 2
  },
  {
    "id": 111710429,
    "createdAt": "2021-10-18T09:17:56.000Z",
    "updatedAt": "2021-11-14T10:51:59.000Z",
    "key": "$PSP_GAME\\USRDIR\\St000\\St006_Cp0501.bin_16",
    "original": "「そこは、ううん、全然…って言うところじゃない？」",
    "translation": "「那个，嗯，完全没…这么说的吧？」",
    "file": 386081,
    "stage": 3,
    "project": 3318,
    "uid": 24520,
    "extra": null,
    "context": "大沢",
    "words": 1
  },
  {
    "id": 111710430,
    "createdAt": "2021-10-18T09:17:56.000Z",
    "updatedAt": "2021-11-14T10:52:00.000Z",
    "key": "$PSP_GAME\\USRDIR\\St000\\St006_Cp0501.bin_17",
    "original": "「う…」",
    "translation": "「唔…」",
    "file": 386081,
    "stage": 3,
    "project": 3318,
    "uid": 24520,
    "extra": null,
    "context": "唯",
    "words": 1
  },
  {
    "id": 111710431,
    "createdAt": "2021-10-18T09:17:56.000Z",
    "updatedAt": "2021-11-14T10:52:02.000Z",
    "key": "$PSP_GAME\\USRDIR\\St000\\St006_Cp0501.bin_18",
    "original": "「ほら、言ってみて」",
    "translation": "「好啦，说出来看看」",
    "file": 386081,
    "stage": 3,
    "project": 3318,
    "uid": 24520,
    "extra": null,
    "context": "大沢",
    "words": 1
  },
  {
    "id": 111710432,
    "createdAt": "2021-10-18T09:17:56.000Z",
    "updatedAt": "2021-11-14T10:52:04.000Z",
    "key": "$PSP_GAME\\USRDIR\\St000\\St006_Cp0501.bin_19",
    "original": "「う…ううん…全然…」",
    "translation": "「没…没有…完全…」",
    "file": 386081,
    "stage": 3,
    "project": 3318,
    "uid": 24520,
    "extra": null,
    "context": "唯",
    "words": 1
  },
  {
    "id": 111710433,
    "createdAt": "2021-10-18T09:17:56.000Z",
    "updatedAt": "2021-11-14T10:52:07.000Z",
    "key": "$PSP_GAME\\USRDIR\\St000\\St006_Cp0501.bin_20",
    "original": "「ふふ、ありがとう」",
    "translation": "「呼呼，谢谢你」",
    "file": 386081,
    "stage": 3,
    "project": 3318,
    "uid": 24520,
    "extra": null,
    "context": "大沢",
    "words": 1
  },
  {
    "id": 111710434,
    "createdAt": "2021-10-18T09:17:56.000Z",
    "updatedAt": "2021-11-14T10:52:09.000Z",
    "key": "$PSP_GAME\\USRDIR\\St000\\St006_Cp0501.bin_21",
    "original": "「――――！」",
    "translation": "「――――！」",
    "file": 386081,
    "stage": 3,
    "project": 3318,
    "uid": 24520,
    "extra": null,
    "context": "唯",
    "words": 1
  },
  {
    "id": 111710435,
    "createdAt": "2021-10-18T09:17:56.000Z",
    "updatedAt": "2021-11-14T10:52:11.000Z",
    "key": "$PSP_GAME\\USRDIR\\St000\\St006_Cp0501.bin_22",
    "original": "「やだ、照れないでよ～」",
    "translation": "「啊呀，不要害羞啦～」",
    "file": 386081,
    "stage": 3,
    "project": 3318,
    "uid": 24520,
    "extra": null,
    "context": "大沢",
    "words": 1
  },
  {
    "id": 111710436,
    "createdAt": "2021-10-18T09:17:56.000Z",
    "updatedAt": "2021-11-14T10:52:12.000Z",
    "key": "$PSP_GAME\\USRDIR\\St000\\St006_Cp0501.bin_23",
    "original": "「う…うん…」",
    "translation": "「额…嗯…」",
    "file": 386081,
    "stage": 3,
    "project": 3318,
    "uid": 24520,
    "extra": null,
    "context": "唯",
    "words": 1
  },
  {
    "id": 111710437,
    "createdAt": "2021-10-18T09:17:56.000Z",
    "updatedAt": "2021-11-14T10:53:17.000Z",
    "key": "$PSP_GAME\\USRDIR\\St000\\St006_Cp0501.bin_24",
    "original": "「うん、バッチリ」",
    "translation": "「嗯，好好说出来」",
    "file": 386081,
    "stage": 3,
    "project": 3318,
    "uid": 24520,
    "extra": null,
    "context": "大沢",
    "words": 1
  },
  {
    "id": 111710438,
    "createdAt": "2021-10-18T09:17:56.000Z",
    "updatedAt": "2021-11-14T10:53:18.000Z",
    "key": "$PSP_GAME\\USRDIR\\St000\\St006_Cp0501.bin_25",
    "original": "「ふふ…」",
    "translation": "「呼呼…」",
    "file": 386081,
    "stage": 3,
    "project": 3318,
    "uid": 24520,
    "extra": null,
    "context": "唯",
    "words": 1
  },
  {
    "id": 111710439,
    "createdAt": "2021-10-18T09:17:56.000Z",
    "updatedAt": "2021-11-14T10:53:21.000Z",
    "key": "$PSP_GAME\\USRDIR\\St000\\St006_Cp0501.bin_26",
    "original": "「え？　どしたの？」",
    "translation": "「诶？ 怎么了？」",
    "file": 386081,
    "stage": 3,
    "project": 3318,
    "uid": 24520,
    "extra": null,
    "context": "大沢",
    "words": 2
  },
  {
    "id": 111710440,
    "createdAt": "2021-10-18T09:17:56.000Z",
    "updatedAt": "2021-11-14T10:53:24.000Z",
    "key": "$PSP_GAME\\USRDIR\\St000\\St006_Cp0501.bin_27",
    "original": "「大沢さんって、人心掌握の達人？」",
    "translation": "「大沢同学，是掌握人心方面的达人？」",
    "file": 386081,
    "stage": 3,
    "project": 3318,
    "uid": 24520,
    "extra": null,
    "context": "唯",
    "words": 1
  },
  {
    "id": 111710441,
    "createdAt": "2021-10-18T09:17:56.000Z",
    "updatedAt": "2021-11-14T11:03:15.000Z",
    "key": "$PSP_GAME\\USRDIR\\St000\\St006_Cp0501.bin_28",
    "original": "「じんしんしょうあく？\\n　何それ？　なんか悪そうな響きだね？」",
    "translation": "「zhangworenxin？\\n　那是啥？听上去像是不太好的词吧？」",
    "file": 386081,
    "stage": 3,
    "project": 3318,
    "uid": 24520,
    "extra": null,
    "context": "大沢",
    "words": 3
  },
  {
    "id": 111710442,
    "createdAt": "2021-10-18T09:17:56.000Z",
    "updatedAt": "2021-11-14T10:54:07.000Z",
    "key": "$PSP_GAME\\USRDIR\\St000\\St006_Cp0501.bin_29",
    "original": "「ぷ！」",
    "translation": "「噗！」",
    "file": 386081,
    "stage": 3,
    "project": 3318,
    "uid": 24520,
    "extra": null,
    "context": "唯",
    "words": 1
  },
  {
    "id": 111710443,
    "createdAt": "2021-10-18T09:17:56.000Z",
    "updatedAt": "2021-11-14T10:54:09.000Z",
    "key": "$PSP_GAME\\USRDIR\\St000\\St006_Cp0501.bin_30",
    "original": "「あはははははは！！」",
    "translation": "「啊哈哈哈哈哈哈！！」",
    "file": 386081,
    "stage": 3,
    "project": 3318,
    "uid": 24520,
    "extra": null,
    "context": "",
    "words": 1
  },
  {
    "id": 111710444,
    "createdAt": "2021-10-18T09:17:56.000Z",
    "updatedAt": "2021-11-14T10:54:10.000Z",
    "key": "$PSP_GAME\\USRDIR\\St000\\St006_Cp0501.bin_31",
    "original": "「え？　え？　なんで笑うの？\\n　なんか変だった？」",
    "translation": "「诶？诶？干嘛笑？\\n　有啥奇怪的吗？」",
    "file": 386081,
    "stage": 3,
    "project": 3318,
    "uid": 24520,
    "extra": null,
    "context": "大沢",
    "words": 4
  },
  {
    "id": 111710445,
    "createdAt": "2021-10-18T09:17:56.000Z",
    "updatedAt": "2021-11-14T10:54:40.000Z",
    "key": "$PSP_GAME\\USRDIR\\St000\\St006_Cp0501.bin_32",
    "original": "「後で調べてみて、じんしんしょうあく」",
    "translation": "「一会自己查吧，zhangworenxin」",
    "file": 386081,
    "stage": 3,
    "project": 3318,
    "uid": 24520,
    "extra": null,
    "context": "唯",
    "words": 1
  },
  {
    "id": 111710446,
    "createdAt": "2021-10-18T09:17:56.000Z",
    "updatedAt": "2021-11-14T10:57:57.000Z",
    "key": "$PSP_GAME\\USRDIR\\St000\\St006_Cp0501.bin_33",
    "original": "「うん、わかった」",
    "translation": "「嗯，知道了」",
    "file": 386081,
    "stage": 3,
    "project": 3318,
    "uid": 24520,
    "extra": null,
    "context": "大沢",
    "words": 1
  },
  {
    "id": 111710447,
    "createdAt": "2021-10-18T09:17:56.000Z",
    "updatedAt": "2021-11-14T10:57:58.000Z",
    "key": "$PSP_GAME\\USRDIR\\St000\\St006_Cp0501.bin_34",
    "original": "「ふふ」",
    "translation": "「呼呼」",
    "file": 386081,
    "stage": 3,
    "project": 3318,
    "uid": 24520,
    "extra": null,
    "context": "唯",
    "words": 1
  },
  {
    "id": 111710448,
    "createdAt": "2021-10-18T09:17:56.000Z",
    "updatedAt": "2021-11-14T10:57:59.000Z",
    "key": "$PSP_GAME\\USRDIR\\St000\\St006_Cp0501.bin_35",
    "original": "「はは」",
    "translation": "「哈哈」",
    "file": 386081,
    "stage": 3,
    "project": 3318,
    "uid": 24520,
    "extra": null,
    "context": "大沢",
    "words": 1
  },
  {
    "id": 111710449,
    "createdAt": "2021-10-18T09:17:56.000Z",
    "updatedAt": "2021-11-14T11:00:44.000Z",
    "key": "$PSP_GAME\\USRDIR\\St000\\St006_Cp0501.bin_36",
    "original": "「う～…」",
    "translation": "「唔～…」",
    "file": 386081,
    "stage": 3,
    "project": 3318,
    "uid": 24520,
    "extra": null,
    "context": "青木",
    "words": 1
  },
  {
    "id": 111710450,
    "createdAt": "2021-10-18T09:17:56.000Z",
    "updatedAt": "2021-11-14T11:00:58.000Z",
    "key": "$PSP_GAME\\USRDIR\\St000\\St006_Cp0501.bin_37",
    "original": "「いいか、青木？\\n　おまえが唯を好きなように大沢だって唯の事が好きなんだ」",
    "translation": "「听好了，青木？\\n　和你喜欢唯一样大沢也喜欢唯」",
    "file": 386081,
    "stage": 3,
    "project": 3318,
    "uid": 24520,
    "extra": null,
    "context": "稲葉",
    "words": 2
  },
  {
    "id": 111710451,
    "createdAt": "2021-10-18T09:17:56.000Z",
    "updatedAt": "2021-11-14T11:01:01.000Z",
    "key": "$PSP_GAME\\USRDIR\\St000\\St006_Cp0501.bin_38",
    "original": "「恋愛は公平であるべきだろう？\\n　ましてやこの時代に性別なんて関係ない」",
    "translation": "「恋爱应该是公平的吧？\\n　都这个时代了，和性别没有关系」",
    "file": 386081,
    "stage": 3,
    "project": 3318,
    "uid": 24520,
    "extra": null,
    "context": "",
    "words": 2
  },
  {
    "id": 111710452,
    "createdAt": "2021-10-18T09:17:56.000Z",
    "updatedAt": "2021-11-14T11:01:49.000Z",
    "key": "$PSP_GAME\\USRDIR\\St000\\St006_Cp0501.bin_39",
    "original": "「それに唯の言葉を思い出してみろ。\\n　あいつは男がまだ怖いんだよ」",
    "translation": "「而且想想唯她自己说过的话吧。\\n　那家伙还很害怕男的啊」",
    "file": 386081,
    "stage": 3,
    "project": 3318,
    "uid": 24520,
    "extra": null,
    "context": "",
    "words": 2
  },
  {
    "id": 111710453,
    "createdAt": "2021-10-18T09:17:56.000Z",
    "updatedAt": "2021-11-14T11:03:48.000Z",
    "key": "$PSP_GAME\\USRDIR\\St000\\St006_Cp0501.bin_40",
    "original": "「友達以上恋人未満ならって言ってるんだ」",
    "translation": "「都说了是友谊以上恋人未满啊」",
    "file": 386081,
    "stage": 3,
    "project": 3318,
    "uid": 24520,
    "extra": null,
    "context": "",
    "words": 1
  },
  {
    "id": 111710454,
    "createdAt": "2021-10-18T09:17:56.000Z",
    "updatedAt": "2021-11-14T11:03:50.000Z",
    "key": "$PSP_GAME\\USRDIR\\St000\\St006_Cp0501.bin_41",
    "original": "「唯の気持ちも尊重するべきじゃないのか？」",
    "translation": "「不应该先尊重唯的想法吗？」",
    "file": 386081,
    "stage": 3,
    "project": 3318,
    "uid": 24520,
    "extra": null,
    "context": "",
    "words": 1
  },
  {
    "id": 111710455,
    "createdAt": "2021-10-18T09:17:56.000Z",
    "updatedAt": "2021-11-14T11:03:52.000Z",
    "key": "$PSP_GAME\\USRDIR\\St000\\St006_Cp0501.bin_42",
    "original": "「そんな事はわかってるよ、稲葉っちゃん！」",
    "translation": "「我知道啊，稻叶酱！」",
    "file": 386081,
    "stage": 3,
    "project": 3318,
    "uid": 24520,
    "extra": null,
    "context": "青木",
    "words": 1
  },
  {
    "id": 111710456,
    "createdAt": "2021-10-18T09:17:56.000Z",
    "updatedAt": "2021-11-14T11:03:55.000Z",
    "key": "$PSP_GAME\\USRDIR\\St000\\St006_Cp0501.bin_43",
    "original": "「けど、なんだあれは！？」",
    "translation": "「但是，那个算什么啊！？」",
    "file": 386081,
    "stage": 3,
    "project": 3318,
    "uid": 24520,
    "extra": null,
    "context": "",
    "words": 1
  },
  {
    "id": 111710457,
    "createdAt": "2021-10-18T09:17:56.000Z",
    "updatedAt": "2021-11-14T11:03:56.000Z",
    "key": "$PSP_GAME\\USRDIR\\St000\\St006_Cp0501.bin_44",
    "original": "「暮れなずむ中、斜陽に映える二人の影！」",
    "translation": "「暮色中，斜阳映照出两人的影子！」",
    "file": 386081,
    "stage": 3,
    "project": 3318,
    "uid": 24520,
    "extra": null,
    "context": "",
    "words": 1
  },
  {
    "id": 111710458,
    "createdAt": "2021-10-18T09:17:56.000Z",
    "updatedAt": "2021-11-14T11:04:03.000Z",
    "key": "$PSP_GAME\\USRDIR\\St000\\St006_Cp0501.bin_45",
    "original": "「大沢さんは背が高いから\\n　唯の小柄さが良い意味で引き立っちゃって、もう！」",
    "translation": "「大沢同学很高\\n　某种意义上衬托出了唯的小身材，真是的！」",
    "file": 386081,
    "stage": 3,
    "project": 3318,
    "uid": 24520,
    "extra": null,
    "context": "",
    "words": 2
  },
  {
    "id": 111710459,
    "createdAt": "2021-10-18T09:17:56.000Z",
    "updatedAt": "2021-11-14T11:04:03.000Z",
    "key": "$PSP_GAME\\USRDIR\\St000\\St006_Cp0501.bin_46",
    "original": "「ぬぐぐ…！」",
    "translation": "「呜咕咕…！」",
    "file": 386081,
    "stage": 3,
    "project": 3318,
    "uid": 24520,
    "extra": null,
    "context": "",
    "words": 1
  },
  {
    "id": 111710460,
    "createdAt": "2021-10-18T09:17:56.000Z",
    "updatedAt": "2021-11-14T11:04:06.000Z",
    "key": "$PSP_GAME\\USRDIR\\St000\\St006_Cp0501.bin_47",
    "original": "「大沢さんって香水つけてるの？」",
    "translation": "「大沢同学喷香水了？」",
    "file": 386081,
    "stage": 3,
    "project": 3318,
    "uid": 24520,
    "extra": null,
    "context": "唯",
    "words": 1
  },
  {
    "id": 111710461,
    "createdAt": "2021-10-18T09:17:56.000Z",
    "updatedAt": "2021-11-14T11:04:14.000Z",
    "key": "$PSP_GAME\\USRDIR\\St000\\St006_Cp0501.bin_48",
    "original": "「ううん、どうして？」",
    "translation": "「没啊，怎么了？」",
    "file": 386081,
    "stage": 3,
    "project": 3318,
    "uid": 24520,
    "extra": null,
    "context": "大沢",
    "words": 1
  },
  {
    "id": 111710462,
    "createdAt": "2021-10-18T09:17:56.000Z",
    "updatedAt": "2021-11-14T11:08:29.000Z",
    "key": "$PSP_GAME\\USRDIR\\St000\\St006_Cp0501.bin_49",
    "original": "「さっき部室の前であたしを抱きとめてくれた時\\n　いい匂いがしたから…」",
    "translation": "「刚才在部室门前抱我的时候\\n　你闻起来很香…」",
    "file": 386081,
    "stage": 3,
    "project": 3318,
    "uid": 24520,
    "extra": null,
    "context": "唯",
    "words": 2
  },
  {
    "id": 111710463,
    "createdAt": "2021-10-18T09:17:56.000Z",
    "updatedAt": "2021-11-14T11:08:42.000Z",
    "key": "$PSP_GAME\\USRDIR\\St000\\St006_Cp0501.bin_50",
    "original": "「ああ、デオドラントスプレーの香りかな？\\n　唯ちゃんは無香料派？」",
    "translation": "「啊，是除臭剂的香味吗？\\n　小唯是无香料派？」",
    "file": 386081,
    "stage": 3,
    "project": 3318,
    "uid": 24520,
    "extra": null,
    "context": "大沢",
    "words": 2
  },
  {
    "id": 111710464,
    "createdAt": "2021-10-18T09:17:56.000Z",
    "updatedAt": "2021-11-14T11:08:57.000Z",
    "key": "$PSP_GAME\\USRDIR\\St000\\St006_Cp0501.bin_51",
    "original": "「あ、うん、そうだね…\\n　って言うか使ってない…」",
    "translation": "「啊，嗯，是啊…\\n　而且我没喷啊…」",
    "file": 386081,
    "stage": 3,
    "project": 3318,
    "uid": 24520,
    "extra": null,
    "context": "唯",
    "words": 2
  },
  {
    "id": 111710465,
    "createdAt": "2021-10-18T09:17:56.000Z",
    "updatedAt": "2021-11-14T11:09:27.000Z",
    "key": "$PSP_GAME\\USRDIR\\St000\\St006_Cp0501.bin_52",
    "original": "「あれ？　空手やってるんでしょ？\\n　そう聞いたけど…」",
    "translation": "「那个？ 你在练空手道吧？\\n　我听说是这样的…」",
    "file": 386081,
    "stage": 3,
    "project": 3318,
    "uid": 24520,
    "extra": null,
    "context": "大沢",
    "words": 3
  },
  {
    "id": 111710466,
    "createdAt": "2021-10-18T09:17:56.000Z",
    "updatedAt": "2021-11-14T11:11:10.000Z",
    "key": "$PSP_GAME\\USRDIR\\St000\\St006_Cp0501.bin_53",
    "original": "「ちょっと…訳あって…\\n　今はやってないの…」",
    "translation": "「那个…发生了些事…\\n　现在不练了…」",
    "file": 386081,
    "stage": 3,
    "project": 3318,
    "uid": 24520,
    "extra": null,
    "context": "唯",
    "words": 2
  },
  {
    "id": 111710467,
    "createdAt": "2021-10-18T09:17:56.000Z",
    "updatedAt": "2021-11-14T11:11:18.000Z",
    "key": "$PSP_GAME\\USRDIR\\St000\\St006_Cp0501.bin_54",
    "original": "「そっか…」",
    "translation": "「这样啊…」",
    "file": 386081,
    "stage": 3,
    "project": 3318,
    "uid": 24520,
    "extra": null,
    "context": "大沢",
    "words": 1
  },
  {
    "id": 111710468,
    "createdAt": "2021-10-18T09:17:56.000Z",
    "updatedAt": "2021-11-14T11:12:46.000Z",
    "key": "$PSP_GAME\\USRDIR\\St000\\St006_Cp0501.bin_55",
    "original": "「だから完全に浦島太郎状態なんだよね、あたし。\\n　今度、おすすめの教えてくれる？」",
    "translation": "「所以完全就是浦岛太郎状态了啊我。\\n　下回推荐我一个呗？？」",
    "file": 386081,
    "stage": 3,
    "project": 3318,
    "uid": 24520,
    "extra": null,
    "context": "唯",
    "words": 2
  },
  {
    "id": 111710469,
    "createdAt": "2021-10-18T09:17:56.000Z",
    "updatedAt": "2021-11-14T11:11:28.000Z",
    "key": "$PSP_GAME\\USRDIR\\St000\\St006_Cp0501.bin_56",
    "original": "「もちろん」",
    "translation": "「当然啦」",
    "file": 386081,
    "stage": 3,
    "project": 3318,
    "uid": 24520,
    "extra": null,
    "context": "大沢",
    "words": 1
  },
  {
    "id": 111710470,
    "createdAt": "2021-10-18T09:17:56.000Z",
    "updatedAt": "2021-11-14T11:11:31.000Z",
    "key": "$PSP_GAME\\USRDIR\\St000\\St006_Cp0501.bin_57",
    "original": "「やった」",
    "translation": "「太好了」",
    "file": 386081,
    "stage": 3,
    "project": 3318,
    "uid": 24520,
    "extra": null,
    "context": "唯",
    "words": 1
  },
  {
    "id": 111710471,
    "createdAt": "2021-10-18T09:17:56.000Z",
    "updatedAt": "2021-11-14T11:13:27.000Z",
    "key": "$PSP_GAME\\USRDIR\\St000\\St006_Cp0501.bin_58",
    "original": "「とりあえずコレ、使ってみれば？\\n　手ぇだして」",
    "translation": "「总之这个，用用看吧？\\n　把手给我」",
    "file": 386081,
    "stage": 3,
    "project": 3318,
    "uid": 24520,
    "extra": null,
    "context": "大沢",
    "words": 2
  },
  {
    "id": 111710472,
    "createdAt": "2021-10-18T09:17:56.000Z",
    "updatedAt": "2021-11-14T11:13:29.000Z",
    "key": "$PSP_GAME\\USRDIR\\St000\\St006_Cp0501.bin_59",
    "original": "「わぁ！　やっぱりいい香り！」",
    "translation": "「哇！果然好香！」",
    "file": 386081,
    "stage": 3,
    "project": 3318,
    "uid": 24520,
    "extra": null,
    "context": "唯",
    "words": 2
  },
  {
    "id": 111710473,
    "createdAt": "2021-10-18T09:17:56.000Z",
    "updatedAt": "2021-11-14T11:13:44.000Z",
    "key": "$PSP_GAME\\USRDIR\\St000\\St006_Cp0501.bin_60",
    "original": "「でしょう？　キツ過ぎないし」",
    "translation": "「对吧？而且也不会太刺鼻」",
    "file": 386081,
    "stage": 3,
    "project": 3318,
    "uid": 24520,
    "extra": null,
    "context": "大沢",
    "words": 2
  },
  {
    "id": 111710474,
    "createdAt": "2021-10-18T09:17:56.000Z",
    "updatedAt": "2021-11-14T11:13:48.000Z",
    "key": "$PSP_GAME\\USRDIR\\St000\\St006_Cp0501.bin_61",
    "original": "「うんうん、やわらかい匂い～！」",
    "translation": "「嗯嗯，一股很柔软的味道～！」",
    "file": 386081,
    "stage": 3,
    "project": 3318,
    "uid": 24520,
    "extra": null,
    "context": "唯",
    "words": 1
  },
  {
    "id": 111710475,
    "createdAt": "2021-10-18T09:17:56.000Z",
    "updatedAt": "2021-11-14T11:16:35.000Z",
    "key": "$PSP_GAME\\USRDIR\\St000\\St006_Cp0501.bin_62",
    "original": "「ってチョー会話もはずんじゃってるんですけど！？」",
    "translation": "「他们这聊的吵欢啊！？」",
    "file": 386081,
    "stage": 3,
    "project": 3318,
    "uid": 24520,
    "extra": null,
    "context": "青木",
    "words": 1
  },
  {
    "id": 111710476,
    "createdAt": "2021-10-18T09:17:56.000Z",
    "updatedAt": "2021-11-14T11:15:02.000Z",
    "key": "$PSP_GAME\\USRDIR\\St000\\St006_Cp0501.bin_63",
    "original": "「声が聞こえなかったら\\n　完全にお似合いのカップルじゃん！？」",
    "translation": "「听不到声音的话\\n　这不完全就像是一对般配情侣了吗！？」",
    "file": 386081,
    "stage": 3,
    "project": 3318,
    "uid": 24520,
    "extra": null,
    "context": "",
    "words": 2
  },
  {
    "id": 111710477,
    "createdAt": "2021-10-18T09:17:56.000Z",
    "updatedAt": "2021-11-14T11:16:43.000Z",
    "key": "$PSP_GAME\\USRDIR\\St000\\St006_Cp0501.bin_64",
    "original": "「やっぱ、ここは惚れた男として一言…！」",
    "translation": "「果然，作为爱她的男人，在这里还是要说句…！」",
    "file": 386081,
    "stage": 3,
    "project": 3318,
    "uid": 24520,
    "extra": null,
    "context": "",
    "words": 1
  },
  {
    "id": 111710478,
    "createdAt": "2021-10-18T09:17:56.000Z",
    "updatedAt": "2021-11-14T11:16:45.000Z",
    "key": "$PSP_GAME\\USRDIR\\St000\\St006_Cp0501.bin_65",
    "original": "「唯の気持ちも尊重するべきじゃないのか？」",
    "translation": "「唯的想法不应该尊重一下吗？」",
    "file": 386081,
    "stage": 3,
    "project": 3318,
    "uid": 24520,
    "extra": null,
    "context": "稲葉",
    "words": 1
  },
  {
    "id": 111710479,
    "createdAt": "2021-10-18T09:17:56.000Z",
    "updatedAt": "2021-11-14T11:16:46.000Z",
    "key": "$PSP_GAME\\USRDIR\\St000\\St006_Cp0501.bin_66",
    "original": "「うっく…！」",
    "translation": "「啊这…！」",
    "file": 386081,
    "stage": 3,
    "project": 3318,
    "uid": 24520,
    "extra": null,
    "context": "青木",
    "words": 1
  },
  {
    "id": 111710480,
    "createdAt": "2021-10-18T09:17:56.000Z",
    "updatedAt": "2021-11-14T11:16:48.000Z",
    "key": "$PSP_GAME\\USRDIR\\St000\\St006_Cp0501.bin_67",
    "original": "「そうだよな…」",
    "translation": "「是啊…」",
    "file": 386081,
    "stage": 3,
    "project": 3318,
    "uid": 24520,
    "extra": null,
    "context": "",
    "words": 1
  },
  {
    "id": 111710481,
    "createdAt": "2021-10-18T09:17:56.000Z",
    "updatedAt": "2021-11-14T11:17:32.000Z",
    "key": "$PSP_GAME\\USRDIR\\St000\\St006_Cp0501.bin_68",
    "original": "「今、ヘタに割り込んで唯の反感でも買おうものなら…\\n　最悪のパターンにだって発展しかねない…」",
    "translation": "「现在，如果插足引起反感的话…\\n　甚至可能发展成最糟糕的样子…」",
    "file": 386081,
    "stage": 3,
    "project": 3318,
    "uid": 24520,
    "extra": null,
    "context": "",
    "words": 2
  },
  {
    "id": 111710482,
    "createdAt": "2021-10-18T09:17:56.000Z",
    "updatedAt": "2021-11-14T11:17:45.000Z",
    "key": "$PSP_GAME\\USRDIR\\St000\\St006_Cp0501.bin_69",
    "original": "「う、オレも唯と\\n　きゃっきゃうふふしたい…」",
    "translation": "「我，我也想和唯\\n　唧唧我我…」",
    "file": 386081,
    "stage": 3,
    "project": 3318,
    "uid": 24520,
    "extra": null,
    "context": "",
    "words": 2
  },
  {
    "id": 111710483,
    "createdAt": "2021-10-18T09:17:56.000Z",
    "updatedAt": "2021-11-14T11:19:04.000Z",
    "key": "$PSP_GAME\\USRDIR\\St000\\St006_Cp0501.bin_70",
    "original": "「きゃ！」",
    "translation": "「呀！」",
    "file": 386081,
    "stage": 3,
    "project": 3318,
    "uid": 24520,
    "extra": null,
    "context": "大沢",
    "words": 1
  },
  {
    "id": 111710484,
    "createdAt": "2021-10-18T09:17:56.000Z",
    "updatedAt": "2021-11-14T11:19:05.000Z",
    "key": "$PSP_GAME\\USRDIR\\St000\\St006_Cp0501.bin_71",
    "original": "「あははは！」",
    "translation": "「啊哈哈哈！」",
    "file": 386081,
    "stage": 3,
    "project": 3318,
    "uid": 24520,
    "extra": null,
    "context": "唯",
    "words": 1
  },
  {
    "id": 111710485,
    "createdAt": "2021-10-18T09:17:56.000Z",
    "updatedAt": "2021-11-14T11:19:24.000Z",
    "key": "$PSP_GAME\\USRDIR\\St000\\St006_Cp0501.bin_72",
    "original": "「やったな～！」",
    "translation": "「真好啊～！」",
    "file": 386081,
    "stage": 3,
    "project": 3318,
    "uid": 24520,
    "extra": null,
    "context": "大沢",
    "words": 1
  },
  {
    "id": 111710486,
    "createdAt": "2021-10-18T09:17:56.000Z",
    "updatedAt": "2021-11-14T11:19:11.000Z",
    "key": "$PSP_GAME\\USRDIR\\St000\\St006_Cp0501.bin_73",
    "original": "「ぬぐぐぐ…くく…！」",
    "translation": "「啊呜呜呜…啊啊…！」",
    "file": 386081,
    "stage": 3,
    "project": 3318,
    "uid": 24520,
    "extra": null,
    "context": "青木",
    "words": 1
  },
  {
    "id": 111710487,
    "createdAt": "2021-10-18T09:17:56.000Z",
    "updatedAt": "2021-11-14T11:19:27.000Z",
    "key": "$PSP_GAME\\USRDIR\\St000\\St006_Cp0501.bin_74",
    "original": "「…………」",
    "translation": "「…………」",
    "file": 386081,
    "stage": 3,
    "project": 3318,
    "uid": 24520,
    "extra": null,
    "context": "",
    "words": 1
  },
  {
    "id": 111710488,
    "createdAt": "2021-10-18T09:17:56.000Z",
    "updatedAt": "2021-11-14T11:20:26.000Z",
    "key": "$PSP_GAME\\USRDIR\\St000\\St006_Cp0501.bin_75",
    "original": "「ダメだ…」",
    "translation": "「不行…」",
    "file": 386081,
    "stage": 3,
    "project": 3318,
    "uid": 24520,
    "extra": null,
    "context": "",
    "words": 1
  },
  {
    "id": 111710489,
    "createdAt": "2021-10-18T09:17:56.000Z",
    "updatedAt": "2021-11-14T11:20:30.000Z",
    "key": "$PSP_GAME\\USRDIR\\St000\\St006_Cp0501.bin_76",
    "original": "「このまま見ててもダメージを食らうだけだな…」",
    "translation": "「就这样看下去我只会受到伤害啊…」",
    "file": 386081,
    "stage": 3,
    "project": 3318,
    "uid": 24520,
    "extra": null,
    "context": "",
    "words": 1
  },
  {
    "id": 111710490,
    "createdAt": "2021-10-18T09:17:56.000Z",
    "updatedAt": "2021-11-14T11:20:31.000Z",
    "key": "$PSP_GAME\\USRDIR\\St000\\St006_Cp0501.bin_77",
    "original": "「今日のところは帰ろう…」",
    "translation": "「今天就到这里回去吧…」",
    "file": 386081,
    "stage": 3,
    "project": 3318,
    "uid": 24520,
    "extra": null,
    "context": "",
    "words": 1
  }
]