[
  {
    "key": "$PSP_GAME\\USRDIR\\St000\\St005_Cp1901.bin_0",
    "original": "放課後",
    "translation": "放学后",
    "stage": 5,
    "context": "Time"
  },
  {
    "key": "$PSP_GAME\\USRDIR\\St000\\St005_Cp1901.bin_1",
    "original": "商店街",
    "translation": "商店街",
    "stage": 5,
    "context": "Location"
  },
  {
    "key": "$PSP_GAME\\USRDIR\\St000\\St005_Cp1901.bin_2",
    "original": "「さーあ、唯の初デート。\\n　どんなオチが待っていますか！」",
    "translation": "「开始ー啦，唯的初次约会。\\n　会有什么样的惨剧呢！」",
    "stage": 3,
    "context": "伊織"
  },
  {
    "key": "$PSP_GAME\\USRDIR\\St000\\St005_Cp1901.bin_3",
    "original": "「オチって……。\\n　青木をオチ担当にするの、やめてやれよ」",
    "translation": "「惨剧……\\n　不要把青木说成什么悲剧角色了啊」",
    "stage": 3,
    "context": "太一"
  },
  {
    "key": "$PSP_GAME\\USRDIR\\St000\\St005_Cp1901.bin_4",
    "original": "「じゃあ、青木がまっとうにデートを進められると思う？」",
    "translation": "「那么，你觉得青木能够正常的约会吗？」",
    "stage": 5,
    "context": "伊織"
  },
  {
    "key": "$PSP_GAME\\USRDIR\\St000\\St005_Cp1901.bin_5",
    "original": "「う、全然想像ができん。\\n　……でも、尾行ってのはどうかと思うぞ」",
    "translation": "「呜，完全不能想象。\\n　……但是，我觉得尾随他们也有点那啥」",
    "stage": 5,
    "context": "太一"
  },
  {
    "key": "$PSP_GAME\\USRDIR\\St000\\St005_Cp1901.bin_6",
    "original": "「アタシだって、\\n　ただ面白がって尾けてるわけじゃねえぞ」",
    "translation": "「我可不是因为想看笑话，\\n　才跟踪他们的哦」",
    "stage": 5,
    "context": "稲葉"
  },
  {
    "key": "$PSP_GAME\\USRDIR\\St000\\St005_Cp1901.bin_7",
    "original": "「青木本人も綺麗さっぱり忘れているが、\\n　青木にはあの予知がある。\\n　２人で外を歩くのは危険だ」",
    "translation": "「虽说青木本人是忘得一干二净了，\\n　但是还有那个预知啊。\\n　就他们两人一起出去很危险的」",
    "stage": 3
  },
  {
    "key": "$PSP_GAME\\USRDIR\\St000\\St005_Cp1901.bin_8",
    "original": "「あ、そうか。\\n　予知のことすっかり忘れてた」",
    "translation": "「啊，对啊。\\n　预知的事完全忘了」",
    "stage": 5,
    "context": "伊織"
  },
  {
    "key": "$PSP_GAME\\USRDIR\\St000\\St005_Cp1901.bin_9",
    "original": "「忘れるなよ……」",
    "translation": "「别忘记啊……」",
    "stage": 5,
    "context": "太一"
  },
  {
    "key": "$PSP_GAME\\USRDIR\\St000\\St005_Cp1901.bin_10",
    "original": "「え～、太一だって忘れてたでしょ？」",
    "translation": "「诶～，太一也忘了的吧？」",
    "stage": 5,
    "context": "伊織"
  },
  {
    "key": "$PSP_GAME\\USRDIR\\St000\\St005_Cp1901.bin_11",
    "original": "「忘れてたなんてことは……\\n　いや、すみません。\\n　青木の作戦に度肝を抜かれてすっかり忘れていました」",
    "translation": "「忘记了什么的……\\n　不，对不起。\\n　光是在意青木的计划所以把那件事都忘光了」",
    "stage": 5,
    "context": "太一"
  },
  {
    "key": "$PSP_GAME\\USRDIR\\St000\\St005_Cp1901.bin_12",
    "original": "「わざわざ認めなくてもいいのに」",
    "translation": "「不用特意去承认啦」",
    "stage": 5,
    "context": "伊織"
  },
  {
    "key": "$PSP_GAME\\USRDIR\\St000\\St005_Cp1901.bin_13",
    "original": "「とにかく！\\n　２人が危険になったら飛び出す。\\n　そうでなければ見守る」",
    "translation": "「总之！\\n　那两人要是遇到危险咱们就冲出去。\\n　在那之前就先在一边看着吧」",
    "stage": 3,
    "context": "稲葉"
  },
  {
    "key": "$PSP_GAME\\USRDIR\\St000\\St005_Cp1901.bin_14",
    "original": "「〈ふうせんかずら〉のクソッタレな予知の犠牲には\\n　させないぞ」",
    "translation": "「不会因为〈风船葛〉的可恶的预知而\\n　牺牲什么的」",
    "stage": 5
  },
  {
    "key": "$PSP_GAME\\USRDIR\\St000\\St005_Cp1901.bin_15",
    "original": "「このデートの最終目標は、\\n　オレと手をつなぐことにしよう。\\n　自然につなげるなら、男も怖くなくなるだろ？」",
    "translation": "「这个约会的最终目标是，\\n　能跟我手牵手。\\n　能自然的做到的话，也就不害怕男生了吧？」",
    "stage": 5,
    "context": "青木"
  },
  {
    "key": "$PSP_GAME\\USRDIR\\St000\\St005_Cp1901.bin_16",
    "original": "「そ、そうね……」",
    "translation": "「是，是啊……」",
    "stage": 5,
    "context": "唯"
  },
  {
    "key": "$PSP_GAME\\USRDIR\\St000\\St005_Cp1901.bin_17",
    "original": "（確かに、手をつなげれば、\\n　触ることが怖いってこともなくなるわよね……\\n　でも、やっぱりまだ……）",
    "translation": "（确实，能牵手的话，\\n　也就不会害怕接触了……\\n　但是，果然还是……）",
    "stage": 5
  },
  {
    "key": "$PSP_GAME\\USRDIR\\St000\\St005_Cp1901.bin_18",
    "original": "「う～ん……」",
    "translation": "「嗯……」",
    "stage": 5,
    "context": "青木"
  },
  {
    "key": "$PSP_GAME\\USRDIR\\St000\\St005_Cp1901.bin_19",
    "original": "「ん？　どうしたの青木？」",
    "translation": "「哎？　怎么了青木？」",
    "stage": 5,
    "context": "唯"
  },
  {
    "key": "$PSP_GAME\\USRDIR\\St000\\St005_Cp1901.bin_20",
    "original": "「やっぱ、ダメだった？　この作戦」",
    "translation": "「果然，不成吗？　这个计划」",
    "stage": 5,
    "context": "青木"
  },
  {
    "key": "$PSP_GAME\\USRDIR\\St000\\St005_Cp1901.bin_21",
    "original": "「今更何言ってるのよ。それに、一泊旅行よりはマシ。\\n　って言うか、付き合ってもいないのに一泊旅行って……。\\n　あんた、何考えてんの？」",
    "translation": "「事到如今还在说什么啊。而且，这可比外宿旅行靠谱多了。\\n　倒不如说，还没有交往就要去外宿旅行……\\n　你，到底在想些什么啊？」",
    "stage": 5,
    "context": "唯"
  },
  {
    "key": "$PSP_GAME\\USRDIR\\St000\\St005_Cp1901.bin_22",
    "original": "「そりゃあ、唯のことだよ。\\n　親睦を深めるには旅行って良いと思わない？」",
    "translation": "「那当然是，唯的事了。\\n　你不觉得为了加深感情而去旅行很合适吗？」",
    "stage": 5,
    "context": "青木"
  },
  {
    "key": "$PSP_GAME\\USRDIR\\St000\\St005_Cp1901.bin_23",
    "original": "「年頃の男女が２人で？」",
    "translation": "「年轻的男女两人？」",
    "stage": 5,
    "context": "唯"
  },
  {
    "key": "$PSP_GAME\\USRDIR\\St000\\St005_Cp1901.bin_24",
    "original": "「いや、それができればいいなーとかは考えもしたけど」",
    "translation": "「不，我觉得要是能那样就好了」",
    "stage": 5,
    "context": "青木"
  },
  {
    "key": "$PSP_GAME\\USRDIR\\St000\\St005_Cp1901.bin_25",
    "original": "「考えてたんだ……」",
    "translation": "「想过啊……」",
    "stage": 5,
    "context": "唯"
  },
  {
    "key": "$PSP_GAME\\USRDIR\\St000\\St005_Cp1901.bin_26",
    "original": "「で、でも……。\\n　２人で同じ部屋にいるのって、\\n　よっぽど親しくなけりゃ気まずいっしょ？」",
    "translation": "「但，但是……\\n　两个人在一个房间，\\n　除非很亲近，不然会很尴尬的吧」",
    "stage": 5,
    "context": "青木"
  },
  {
    "key": "$PSP_GAME\\USRDIR\\St000\\St005_Cp1901.bin_27",
    "original": "「その気まずさを乗り越えられれば、\\n　少なくともオレに対しての恐怖は\\n　乗り越えられるかなーって思ったんだけど」",
    "translation": "「只要能跨越这个尴尬，\\n　我觉得至少能克服的了\\n　你对我的恐惧了吧」",
    "stage": 5
  },
  {
    "key": "$PSP_GAME\\USRDIR\\St000\\St005_Cp1901.bin_28",
    "original": "「あ、あー。\\n　そうね、なるほどね」",
    "translation": "「啊，啊ー。\\n　是啊，原来如此」",
    "stage": 5,
    "context": "唯"
  },
  {
    "key": "$PSP_GAME\\USRDIR\\St000\\St005_Cp1901.bin_29",
    "original": "「でも、一泊旅行になったとしても、\\n　オレが何もしないってのは本当だから」",
    "translation": "「但是，就算是外宿旅行，\\n　我真的什么都不会做的」",
    "stage": 5,
    "context": "青木"
  },
  {
    "key": "$PSP_GAME\\USRDIR\\St000\\St005_Cp1901.bin_30",
    "original": "「オレ、唯が傷つくようなことだけは\\n　したくないと思ってるから！」",
    "translation": "「我，肯定不会去做\\n　伤害到唯的事的！」",
    "stage": 5
  },
  {
    "key": "$PSP_GAME\\USRDIR\\St000\\St005_Cp1901.bin_31",
    "original": "「……それも今更よ。そんなの、分かってる」",
    "translation": "「……都到现在了。那种事，我当然知道了」",
    "stage": 5,
    "context": "唯"
  },
  {
    "key": "$PSP_GAME\\USRDIR\\St000\\St005_Cp1901.bin_32",
    "original": "（これだけ気にかけてくれるのに……。\\n　あたしが大沢さんと仲良くしてたのを\\n　黙って見てた青木……）",
    "translation": "（明明就这么在意我……\\n　却还一直默默地看着我跟大泽同学的关系\\n　越变越好……）",
    "stage": 5
  },
  {
    "key": "$PSP_GAME\\USRDIR\\St000\\St005_Cp1901.bin_33",
    "original": "（青木なら、あたしが嫌がることは、\\n　絶対しない……）",
    "translation": "（青木的话，那些会让我讨厌的事，\\n　他是绝对不会做的……）",
    "stage": 5
  },
  {
    "key": "$PSP_GAME\\USRDIR\\St000\\St005_Cp1901.bin_34",
    "original": "（本当に、そういうときが来て、\\n　あたしが嫌だって言えば、\\n　絶対、やめてくれる……）",
    "translation": "（真的，要真到了那个时候的话，\\n　我要是说不想，\\n　他就绝对，不会做的……）",
    "stage": 5
  },
  {
    "key": "$PSP_GAME\\USRDIR\\St000\\St005_Cp1901.bin_35",
    "original": "（そんな青木に、あたしができることは……）",
    "translation": "（对这样的青木，我能做到的事是……）",
    "stage": 5
  },
  {
    "key": "$PSP_GAME\\USRDIR\\St000\\St005_Cp1901.bin_36",
    "original": "「あたし、あんな予知、実現させないからね」",
    "translation": "「我，绝对不会让，那种预知发生的」",
    "stage": 5
  },
  {
    "key": "$PSP_GAME\\USRDIR\\St000\\St005_Cp1901.bin_37",
    "original": "「あっ、そうか。\\n　フルボッコにされる予知のこと、すっかり忘れてた」",
    "translation": "「啊，对。\\n　被揍得很惨的预知那事，我完全忘了」",
    "stage": 5,
    "context": "青木"
  },
  {
    "key": "$PSP_GAME\\USRDIR\\St000\\St005_Cp1901.bin_38",
    "original": "「あんたらしいわね……」",
    "translation": "「真是有你的风格啊……」",
    "stage": 5,
    "context": "唯"
  },
  {
    "key": "$PSP_GAME\\USRDIR\\St000\\St005_Cp1901.bin_39",
    "original": "「でも、必ず、助けてあげる。\\n　それが、今のあたしがあんたにしてあげられる、\\n　１番のことだと思うから」",
    "translation": "「但，我肯定会帮你的。\\n　那是，现在的我能为你做的事情里\\n　最想为你做的事」",
    "stage": 5
  },
  {
    "key": "$PSP_GAME\\USRDIR\\St000\\St005_Cp1901.bin_40",
    "original": "「うん。\\n　でも、危なくなったら\\n　オレを捨てて逃げるって約束して欲しい」",
    "translation": "「嗯。\\n　但是，希望你能跟我约定好，要是很危险的话\\n　你要抛下我逃走」",
    "stage": 5,
    "context": "青木"
  },
  {
    "key": "$PSP_GAME\\USRDIR\\St000\\St005_Cp1901.bin_41",
    "original": "「オレはボコボコになろうがどうされようが構わないけど、\\n　唯はケガしちゃいけないんだからな」",
    "translation": "「不用在意我会不会被揍得很惨，\\n　我不想让唯受伤啊」",
    "stage": 5
  }
]