[
  {
    "id": 111715300,
    "createdAt": "2021-10-18T09:18:38.000Z",
    "updatedAt": "2021-11-27T11:10:48.000Z",
    "key": "$PSP_GAME\\USRDIR\\St000\\St106_Cp0001.bin_0",
    "original": "放課後",
    "translation": "放学后",
    "file": 386170,
    "stage": 5,
    "project": 3318,
    "uid": 24816,
    "extra": null,
    "context": "Time",
    "words": 1
  },
  {
    "id": 111715301,
    "createdAt": "2021-10-18T09:18:38.000Z",
    "updatedAt": "2021-11-11T08:26:31.000Z",
    "key": "$PSP_GAME\\USRDIR\\St000\\St106_Cp0001.bin_1",
    "original": "部室",
    "translation": "活动室",
    "file": 386170,
    "stage": 5,
    "project": 3318,
    "uid": 24520,
    "extra": null,
    "context": "Location",
    "words": 1
  },
  {
    "id": 111715302,
    "createdAt": "2021-10-18T09:18:38.000Z",
    "updatedAt": "2021-11-27T11:10:58.000Z",
    "key": "$PSP_GAME\\USRDIR\\St000\\St106_Cp0001.bin_2",
    "original": "〈ふうせんかずら〉が現れた翌日、\\n俺達は普通に部室に集まっていた。",
    "translation": "〈风船葛〉出现后的第二天，\\n我们几个仍旧像平常一样来到活动室集合。",
    "file": 386170,
    "stage": 5,
    "project": 3318,
    "uid": 24816,
    "extra": null,
    "context": "太一",
    "words": 2
  },
  {
    "id": 111715303,
    "createdAt": "2021-10-18T09:18:38.000Z",
    "updatedAt": "2021-11-27T11:11:40.000Z",
    "key": "$PSP_GAME\\USRDIR\\St000\\St106_Cp0001.bin_3",
    "original": "それは、始まってしまったものは仕方がないという\\nあきらめの気持ちもあったが……、",
    "translation": "在一种对已经开始之事感到无可奈何的\\n自暴自弃的心理……，",
    "file": 386170,
    "stage": 5,
    "project": 3318,
    "uid": 24816,
    "extra": null,
    "context": "",
    "words": 2
  },
  {
    "id": 111715304,
    "createdAt": "2021-10-18T09:18:38.000Z",
    "updatedAt": "2021-11-27T11:11:39.000Z",
    "key": "$PSP_GAME\\USRDIR\\St000\\St106_Cp0001.bin_4",
    "original": "稲葉の『奴の力からは、逃れられる気がしない。\\n前回を例にすれば、一ヶ月ほどで終わるんだ。\\nだったら、少しでも普通に過ごしていた方が身のためだ』",
    "translation": "以及稻叶所说的『想逃出那家伙的手掌心，恐怕是不可能的。\\n以上回的事件为参照的话，差不多一个月就能结束。\\n既然如此，不如尽量像平常一样，普通度日，这也是为了咱们自己好』",
    "file": 386170,
    "stage": 5,
    "project": 3318,
    "uid": 24816,
    "extra": null,
    "context": "",
    "words": 3
  },
  {
    "id": 111715305,
    "createdAt": "2021-10-18T09:18:38.000Z",
    "updatedAt": "2021-11-27T11:12:03.000Z",
    "key": "$PSP_GAME\\USRDIR\\St000\\St106_Cp0001.bin_5",
    "original": "……という一言があったこともあり、\\nみんなが、『だったら、やるしかないか……』という\\n気持ちになったのが大きいだろう。",
    "translation": "……这一番话的影响之下，\\n大家都陷入了『既然如此，那就走一步算一步……』的情绪之中，\\n这就是大家不为所动的主要原因吧。",
    "file": 386170,
    "stage": 5,
    "project": 3318,
    "uid": 24816,
    "extra": null,
    "context": "",
    "words": 3
  },
  {
    "id": 111715306,
    "createdAt": "2021-10-18T09:18:38.000Z",
    "updatedAt": "2021-11-27T11:12:04.000Z",
    "key": "$PSP_GAME\\USRDIR\\St000\\St106_Cp0001.bin_6",
    "original": "……その気持ちが大きいんだが、だからと言って、\\nこの状況はちょっと緩みすぎのような気もする。",
    "translation": "……虽然主要原因在于这种情绪，但再怎么说，\\n现在这副景象似乎也有些放松过头了。",
    "file": 386170,
    "stage": 5,
    "project": 3318,
    "uid": 24816,
    "extra": null,
    "context": "",
    "words": 2
  },
  {
    "id": 111715307,
    "createdAt": "2021-10-18T09:18:38.000Z",
    "updatedAt": "2021-11-27T11:12:19.000Z",
    "key": "$PSP_GAME\\USRDIR\\St000\\St106_Cp0001.bin_7",
    "original": "「はふぅ～、食欲の秋だよね～。\\n　もぐもぐもぐ……」",
    "translation": "「哈呼～，到食欲之秋了呢～。\\n　呜咕呜咕呜咕……」",
    "file": 386170,
    "stage": 5,
    "project": 3318,
    "uid": 24816,
    "extra": null,
    "context": "伊織",
    "words": 2
  },
  {
    "id": 111715308,
    "createdAt": "2021-10-18T09:18:38.000Z",
    "updatedAt": "2021-11-27T11:12:21.000Z",
    "key": "$PSP_GAME\\USRDIR\\St000\\St106_Cp0001.bin_8",
    "original": "「そうよね～。もぐもぐ……。\\n　ぶわぁ、このスイートポテト美味しいっ！」",
    "translation": "「是啊～。呜咕呜咕……。\\n　噗啊，这红薯真好吃！」",
    "file": 386170,
    "stage": 5,
    "project": 3318,
    "uid": 24816,
    "extra": null,
    "context": "唯",
    "words": 2
  },
  {
    "id": 111715309,
    "createdAt": "2021-10-18T09:18:38.000Z",
    "updatedAt": "2021-11-27T11:12:31.000Z",
    "key": "$PSP_GAME\\USRDIR\\St000\\St106_Cp0001.bin_9",
    "original": "「どれどれ、アタシもひとつ……。もぐもぐ……。\\n　んん！　案外イケるな、これは！」",
    "translation": "「给我也整一个……。呜咕呜咕……。\\n　嗯嗯！　不可貌相啊，这东西！」",
    "file": 386170,
    "stage": 5,
    "project": 3318,
    "uid": 24816,
    "extra": null,
    "context": "稲葉",
    "words": 3
  },
  {
    "id": 111715310,
    "createdAt": "2021-10-18T09:18:38.000Z",
    "updatedAt": "2021-11-27T11:12:51.000Z",
    "key": "$PSP_GAME\\USRDIR\\St000\\St106_Cp0001.bin_10",
    "original": "「でしょ～？\\n　この間雑誌に載ってたお店の奴なんだ～！\\n　お取り寄せしてたのが、ちょうど昨日来たのよ」",
    "translation": "「是吧～？\\n　前段时间上过杂志的那家店的哦～！\\n　正好昨天刚进的新货」",
    "file": 386170,
    "stage": 5,
    "project": 3318,
    "uid": 24816,
    "extra": null,
    "context": "唯",
    "words": 3
  },
  {
    "id": 111715311,
    "createdAt": "2021-10-18T09:18:38.000Z",
    "updatedAt": "2021-11-27T11:13:18.000Z",
    "key": "$PSP_GAME\\USRDIR\\St000\\St106_Cp0001.bin_11",
    "original": "「さすが唯！\\n　この手のチェックはぬかりないね」",
    "translation": "「不愧是唯！\\n　在这方面真是无懈可击啊」",
    "file": 386170,
    "stage": 5,
    "project": 3318,
    "uid": 24816,
    "extra": null,
    "context": "伊織",
    "words": 2
  },
  {
    "id": 111715312,
    "createdAt": "2021-10-18T09:18:38.000Z",
    "updatedAt": "2021-11-27T11:13:23.000Z",
    "key": "$PSP_GAME\\USRDIR\\St000\\St106_Cp0001.bin_12",
    "original": "「んふふふ。ほめてほめて！\\n　あ、でも伊織が持ってきた、この和菓子も美味しいよね！」",
    "translation": "「嗯呼呼呼。多夸点多夸点！\\n　啊，但是伊织你带来的这个日式点心也很好吃啊！」",
    "file": 386170,
    "stage": 5,
    "project": 3318,
    "uid": 24816,
    "extra": null,
    "context": "唯",
    "words": 2
  },
  {
    "id": 111715313,
    "createdAt": "2021-10-18T09:18:38.000Z",
    "updatedAt": "2021-11-27T11:13:28.000Z",
    "key": "$PSP_GAME\\USRDIR\\St000\\St106_Cp0001.bin_13",
    "original": "「そうだな。洋菓子には無い、この上品な味わいがまた……」",
    "translation": "「是啊，这种洋点心没有的高贵的口感……」",
    "file": 386170,
    "stage": 5,
    "project": 3318,
    "uid": 24816,
    "extra": null,
    "context": "稲葉",
    "words": 1
  },
  {
    "id": 111715314,
    "createdAt": "2021-10-18T09:18:38.000Z",
    "updatedAt": "2021-11-27T11:13:32.000Z",
    "key": "$PSP_GAME\\USRDIR\\St000\\St106_Cp0001.bin_14",
    "original": "「あ～、それねぇ。\\n　お母さんが、昨日、事務所で貰ってきた奴なんだ～」",
    "translation": "「啊～，那个啊。\\n　那个是我妈昨天从单位带回来的哦～」",
    "file": 386170,
    "stage": 5,
    "project": 3318,
    "uid": 24816,
    "extra": null,
    "context": "伊織",
    "words": 2
  },
  {
    "id": 111715315,
    "createdAt": "2021-10-18T09:18:38.000Z",
    "updatedAt": "2021-11-27T11:13:41.000Z",
    "key": "$PSP_GAME\\USRDIR\\St000\\St106_Cp0001.bin_15",
    "original": "「なんかお得意さんから、\\n　いっぱい貰ったとかなんとかで……」",
    "translation": "「好像是说有个常客，\\n　送了一大堆过来什么的……」",
    "file": 386170,
    "stage": 5,
    "project": 3318,
    "uid": 24816,
    "extra": null,
    "context": "",
    "words": 2
  },
  {
    "id": 111715316,
    "createdAt": "2021-10-18T09:18:38.000Z",
    "updatedAt": "2021-11-27T11:13:42.000Z",
    "key": "$PSP_GAME\\USRDIR\\St000\\St106_Cp0001.bin_16",
    "original": "「へぇ～……」",
    "translation": "「诶～……」",
    "file": 386170,
    "stage": 5,
    "project": 3318,
    "uid": 24816,
    "extra": null,
    "context": "唯",
    "words": 1
  },
  {
    "id": 111715317,
    "createdAt": "2021-10-18T09:18:38.000Z",
    "updatedAt": "2021-11-27T11:13:47.000Z",
    "key": "$PSP_GAME\\USRDIR\\St000\\St106_Cp0001.bin_17",
    "original": "「でも、稲葉んが持ってきたクッキーも美味しいよね。\\n　これって、結構高いんじゃない？」",
    "translation": "「但是稻叶儿带过来的饼干也很好吃呢。\\n　这个好像还挺贵的吧？」",
    "file": 386170,
    "stage": 5,
    "project": 3318,
    "uid": 24816,
    "extra": null,
    "context": "伊織",
    "words": 2
  },
  {
    "id": 111715318,
    "createdAt": "2021-10-18T09:18:38.000Z",
    "updatedAt": "2021-11-27T11:13:51.000Z",
    "key": "$PSP_GAME\\USRDIR\\St000\\St106_Cp0001.bin_18",
    "original": "「そうだな。コレも貰いもんだとか言ってたが、\\n　いつも家にあるから、値段を気にしたことは無いな」\\n　",
    "translation": "「不清楚。这个也是别人送的，\\n　一直放在家里，所以也没在意过价格」\\n",
    "file": 386170,
    "stage": 5,
    "project": 3318,
    "uid": 24816,
    "extra": null,
    "context": "稲葉",
    "words": 2
  },
  {
    "id": 111715319,
    "createdAt": "2021-10-18T09:18:38.000Z",
    "updatedAt": "2021-11-27T11:13:54.000Z",
    "key": "$PSP_GAME\\USRDIR\\St000\\St106_Cp0001.bin_19",
    "original": "「そうなんだ？\\n　なんか、さすが稲葉の家って感じよね！」",
    "translation": "「这样啊？\\n　有种不愧是稻叶家的感觉！」",
    "file": 386170,
    "stage": 5,
    "project": 3318,
    "uid": 24816,
    "extra": null,
    "context": "唯",
    "words": 2
  },
  {
    "id": 111715320,
    "createdAt": "2021-10-18T09:18:38.000Z",
    "updatedAt": "2021-11-27T11:14:16.000Z",
    "key": "$PSP_GAME\\USRDIR\\St000\\St106_Cp0001.bin_20",
    "original": "「何がどうなると、アタシの家って感じなんだ？」",
    "translation": "「什么东西，怎么了就有我家的感觉了？」",
    "file": 386170,
    "stage": 5,
    "project": 3318,
    "uid": 24816,
    "extra": null,
    "context": "稲葉",
    "words": 1
  },
  {
    "id": 111715321,
    "createdAt": "2021-10-18T09:18:38.000Z",
    "updatedAt": "2021-11-27T11:14:25.000Z",
    "key": "$PSP_GAME\\USRDIR\\St000\\St106_Cp0001.bin_21",
    "original": "「まぁまぁ、稲葉ん。\\n　そんな細かい事は良いじゃん？\\n　ささ、スイートポテトをもうひとつどうぞ！」",
    "translation": "「嘛嘛，稻叶儿。\\n　那种小事没必要在意啦？\\n　撒撒，再来个红薯！」",
    "file": 386170,
    "stage": 5,
    "project": 3318,
    "uid": 24816,
    "extra": null,
    "context": "伊織",
    "words": 3
  },
  {
    "id": 111715322,
    "createdAt": "2021-10-18T09:18:38.000Z",
    "updatedAt": "2021-11-27T11:14:27.000Z",
    "key": "$PSP_GAME\\USRDIR\\St000\\St106_Cp0001.bin_22",
    "original": "「お、悪いな」",
    "translation": "「哦，谢了」",
    "file": 386170,
    "stage": 5,
    "project": 3318,
    "uid": 24816,
    "extra": null,
    "context": "稲葉",
    "words": 1
  },
  {
    "id": 111715323,
    "createdAt": "2021-10-18T09:18:38.000Z",
    "updatedAt": "2021-11-27T11:15:27.000Z",
    "key": "$PSP_GAME\\USRDIR\\St000\\St106_Cp0001.bin_23",
    "original": "「お、おい、お前ら。\\n　いくら普段通り過ごすのが良いと言っても、\\n　それは、あまりにのんびりしすぎじゃないか？」",
    "translation": "「喂、喂，你们几个。\\n　虽然确实说过像平时一样就好，\\n　但你们现在这样也未免太放松了点吧？」",
    "file": 386170,
    "stage": 5,
    "project": 3318,
    "uid": 24816,
    "extra": null,
    "context": "太一",
    "words": 3
  },
  {
    "id": 111715324,
    "createdAt": "2021-10-18T09:18:38.000Z",
    "updatedAt": "2021-11-27T11:15:30.000Z",
    "key": "$PSP_GAME\\USRDIR\\St000\\St106_Cp0001.bin_24",
    "original": "「……っていうか、いつもこんな事してないよね？」",
    "translation": "「……更何况，你们平时也不干这种事啊？」",
    "file": 386170,
    "stage": 5,
    "project": 3318,
    "uid": 24816,
    "extra": null,
    "context": "青木",
    "words": 1
  },
  {
    "id": 111715325,
    "createdAt": "2021-10-18T09:18:38.000Z",
    "updatedAt": "2021-11-27T11:15:38.000Z",
    "key": "$PSP_GAME\\USRDIR\\St000\\St106_Cp0001.bin_25",
    "original": "「なに～？　太一達も欲しいの？\\n　好きなの持ってっていいよ～？」",
    "translation": "「怎么～？　太一你们俩也想要吗？\\n　想要什么就来拿吧～？」",
    "file": 386170,
    "stage": 5,
    "project": 3318,
    "uid": 24816,
    "extra": null,
    "context": "伊織",
    "words": 3
  },
  {
    "id": 111715326,
    "createdAt": "2021-10-18T09:18:38.000Z",
    "updatedAt": "2021-11-27T11:16:44.000Z",
    "key": "$PSP_GAME\\USRDIR\\St000\\St106_Cp0001.bin_26",
    "original": "「いや、そういう問題じゃなくてだな。\\n　なんというか、そんなに食ってると太るぞ？」",
    "translation": "「不是，问题不在那。\\n　该怎么说呢，吃那么多会胖的哦？」",
    "file": 386170,
    "stage": 5,
    "project": 3318,
    "uid": 24816,
    "extra": null,
    "context": "太一",
    "words": 2
  },
  {
    "id": 111715327,
    "createdAt": "2021-10-18T09:18:38.000Z",
    "updatedAt": "2021-11-27T11:16:56.000Z",
    "key": "$PSP_GAME\\USRDIR\\St000\\St106_Cp0001.bin_27",
    "original": "「大丈夫、大丈夫、そうそう太らないわよ。\\n　……って言うか、こんな状況、\\n　食べないとやってらんないわよ！」",
    "translation": "「没事，没事，不会这么容易就胖的啦。\\n　……不如说，现在这种状况，\\n　不吃东西怎么熬得过去啊！」",
    "file": 386170,
    "stage": 5,
    "project": 3318,
    "uid": 24816,
    "extra": null,
    "context": "唯",
    "words": 3
  },
  {
    "id": 111715328,
    "createdAt": "2021-10-18T09:18:38.000Z",
    "updatedAt": "2021-11-27T11:17:06.000Z",
    "key": "$PSP_GAME\\USRDIR\\St000\\St106_Cp0001.bin_28",
    "original": "「それは、そうかも知れないが……」",
    "translation": "「话是这么说……」",
    "file": 386170,
    "stage": 5,
    "project": 3318,
    "uid": 24816,
    "extra": null,
    "context": "太一",
    "words": 1
  },
  {
    "id": 111715329,
    "createdAt": "2021-10-18T09:18:38.000Z",
    "updatedAt": "2021-11-27T11:17:16.000Z",
    "key": "$PSP_GAME\\USRDIR\\St000\\St106_Cp0001.bin_29",
    "original": "「はぁ～。ぽっちゃりした唯か～。\\n　それはそれで、柔らかそうで可愛いんだろうなぁ～…」",
    "translation": "「哈～。胖乎乎的唯啊～。\\n　这软软的感觉，也别有一番可爱呢～…」",
    "file": 386170,
    "stage": 5,
    "project": 3318,
    "uid": 24816,
    "extra": null,
    "context": "青木",
    "words": 2
  },
  {
    "id": 111715330,
    "createdAt": "2021-10-18T09:18:38.000Z",
    "updatedAt": "2021-11-27T11:18:21.000Z",
    "key": "$PSP_GAME\\USRDIR\\St000\\St106_Cp0001.bin_30",
    "original": "「気持ち悪い想像してんじゃねえよ、青木！」",
    "translation": "「停止你那恶心的妄想，青木！」",
    "file": 386170,
    "stage": 5,
    "project": 3318,
    "uid": 24816,
    "extra": null,
    "context": "稲葉",
    "words": 1
  },
  {
    "id": 111715331,
    "createdAt": "2021-10-18T09:18:38.000Z",
    "updatedAt": "2021-11-27T11:18:33.000Z",
    "key": "$PSP_GAME\\USRDIR\\St000\\St106_Cp0001.bin_31",
    "original": "「そうよ！　あたしが太るわけないでしょ！\\n　空手やってたときだって、ご飯いっぱい食べてたけど、\\n　まったく太らなかったんだからっ！」",
    "translation": "「就是嘛！　我才不可能胖呢！\\n　练空手道那会也是，每天就算吃很多，\\n　也完全没胖起来啊！」",
    "file": 386170,
    "stage": 5,
    "project": 3318,
    "uid": 24816,
    "extra": null,
    "context": "唯",
    "words": 4
  },
  {
    "id": 111715332,
    "createdAt": "2021-10-18T09:18:38.000Z",
    "updatedAt": "2021-11-27T11:18:44.000Z",
    "key": "$PSP_GAME\\USRDIR\\St000\\St106_Cp0001.bin_32",
    "original": "「まぁ、太る太らないはともかくさ、\\n　もう〈ふうせんかずら〉の現象が始まっちゃったんだから、\\n　終わるまで頑張るしかないじゃん？」",
    "translation": "「嘛，先不管胖不胖，\\n　〈风船葛〉引发的现象已经开始了，\\n　也只能努力到事件结束了不是吗？」",
    "file": 386170,
    "stage": 5,
    "project": 3318,
    "uid": 24816,
    "extra": null,
    "context": "伊織",
    "words": 3
  },
  {
    "id": 111715333,
    "createdAt": "2021-10-18T09:18:38.000Z",
    "updatedAt": "2021-11-27T11:19:05.000Z",
    "key": "$PSP_GAME\\USRDIR\\St000\\St106_Cp0001.bin_33",
    "original": "「そうだ。\\n　現状、『人格入れ替わり』のときに比べれば、\\n　日常生活に影響は無いしな」",
    "translation": "「没错。\\n　目前，与『人格交换』的时候相比，\\n　并没有影响到日常生活」",
    "file": 386170,
    "stage": 5,
    "project": 3318,
    "uid": 24816,
    "extra": null,
    "context": "稲葉",
    "words": 3
  },
  {
    "id": 111715334,
    "createdAt": "2021-10-18T09:18:38.000Z",
    "updatedAt": "2021-11-27T11:26:00.000Z",
    "key": "$PSP_GAME\\USRDIR\\St000\\St106_Cp0001.bin_34",
    "original": "「せいぜい、どんな未来を見せられても、\\n　冷静に対処できるように、今は英気を養っておくのが、\\n　得策だ。伊織、この羊羹、もうひとつ貰うぞ？」",
    "translation": "「现在我们能做的，充其量也只有养精蓄锐，\\n　以便不论被呈现怎样的未来，都能冷静应对。\\n　伊织，这个羊羹，我再吃一个哦？」",
    "file": 386170,
    "stage": 5,
    "project": 3318,
    "uid": 24816,
    "extra": null,
    "context": "",
    "words": 3
  },
  {
    "id": 111715335,
    "createdAt": "2021-10-18T09:18:38.000Z",
    "updatedAt": "2021-11-27T11:26:15.000Z",
    "key": "$PSP_GAME\\USRDIR\\St000\\St106_Cp0001.bin_35",
    "original": "「そ、そんなものか……？」",
    "translation": "「是，是这样吗……？」",
    "file": 386170,
    "stage": 5,
    "project": 3318,
    "uid": 24816,
    "extra": null,
    "context": "太一",
    "words": 1
  },
  {
    "id": 111715336,
    "createdAt": "2021-10-18T09:18:38.000Z",
    "updatedAt": "2021-11-27T11:26:26.000Z",
    "key": "$PSP_GAME\\USRDIR\\St000\\St106_Cp0001.bin_36",
    "original": "「ま、稲葉っちゃんが、そう言うんなら、\\n　それが一番なんだろうぜ。\\n　ってなわけで、オレ達も菓子食おう太一！」",
    "translation": "「嘛，既然稻叶酱这么说，\\n　那就是最好的方案咯。\\n　所以说，咱俩也开吃吧太一！」",
    "file": 386170,
    "stage": 5,
    "project": 3318,
    "uid": 24816,
    "extra": null,
    "context": "青木",
    "words": 3
  },
  {
    "id": 111715337,
    "createdAt": "2021-10-18T09:18:38.000Z",
    "updatedAt": "2021-11-27T11:26:28.000Z",
    "key": "$PSP_GAME\\USRDIR\\St000\\St106_Cp0001.bin_37",
    "original": "「お、おう…」",
    "translation": "「哦，哦……」",
    "file": 386170,
    "stage": 5,
    "project": 3318,
    "uid": 24816,
    "extra": null,
    "context": "太一",
    "words": 1
  }
]