[
  {
    "id": 111717144,
    "createdAt": "2021-10-18T09:18:52.000Z",
    "updatedAt": null,
    "key": "$PSP_GAME\\USRDIR\\St000\\St109_Cp0002.bin_0",
    "original": "朝",
    "translation": "",
    "file": 386199,
    "stage": 0,
    "project": 3318,
    "uid": null,
    "extra": null,
    "context": "Time",
    "words": 1
  },
  {
    "id": 111717145,
    "createdAt": "2021-10-18T09:18:52.000Z",
    "updatedAt": null,
    "key": "$PSP_GAME\\USRDIR\\St000\\St109_Cp0002.bin_1",
    "original": "交差点",
    "translation": "",
    "file": 386199,
    "stage": 0,
    "project": 3318,
    "uid": null,
    "extra": null,
    "context": "Location",
    "words": 1
  },
  {
    "id": 111717146,
    "createdAt": "2021-10-18T09:18:52.000Z",
    "updatedAt": null,
    "key": "$PSP_GAME\\USRDIR\\St000\\St109_Cp0002.bin_2",
    "original": "「青木のことが解決したのはいいことだけど、\\n　また変な問題が出てきたなぁ……」",
    "translation": "",
    "file": 386199,
    "stage": 0,
    "project": 3318,
    "uid": null,
    "extra": null,
    "context": "唯",
    "words": 2
  },
  {
    "id": 111717147,
    "createdAt": "2021-10-18T09:18:52.000Z",
    "updatedAt": null,
    "key": "$PSP_GAME\\USRDIR\\St000\\St109_Cp0002.bin_3",
    "original": "（でも、雪菜には彼氏がいるし。\\n　きっと気のせいよね、うん。そうに決まってるわ！）",
    "translation": "",
    "file": 386199,
    "stage": 0,
    "project": 3318,
    "uid": null,
    "extra": null,
    "context": "",
    "words": 2
  },
  {
    "id": 111717148,
    "createdAt": "2021-10-18T09:18:52.000Z",
    "updatedAt": null,
    "key": "$PSP_GAME\\USRDIR\\St000\\St109_Cp0002.bin_4",
    "original": "「あれ、唯じゃん。おっはよー」",
    "translation": "",
    "file": 386199,
    "stage": 0,
    "project": 3318,
    "uid": null,
    "extra": null,
    "context": "雪菜",
    "words": 1
  },
  {
    "id": 111717149,
    "createdAt": "2021-10-18T09:18:52.000Z",
    "updatedAt": null,
    "key": "$PSP_GAME\\USRDIR\\St000\\St109_Cp0002.bin_5",
    "original": "「うおおおっとーーいっ！？」",
    "translation": "",
    "file": 386199,
    "stage": 0,
    "project": 3318,
    "uid": null,
    "extra": null,
    "context": "唯",
    "words": 1
  },
  {
    "id": 111717150,
    "createdAt": "2021-10-18T09:18:52.000Z",
    "updatedAt": null,
    "key": "$PSP_GAME\\USRDIR\\St000\\St109_Cp0002.bin_6",
    "original": "「……あ、ゆ、雪菜……？　お、おはよう」",
    "translation": "",
    "file": 386199,
    "stage": 0,
    "project": 3318,
    "uid": null,
    "extra": null,
    "context": "",
    "words": 2
  },
  {
    "id": 111717151,
    "createdAt": "2021-10-18T09:18:52.000Z",
    "updatedAt": null,
    "key": "$PSP_GAME\\USRDIR\\St000\\St109_Cp0002.bin_7",
    "original": "「あんた見た目も中身も可愛いくせに、\\n　どうしてそんな変な声をあげるのよ？」",
    "translation": "",
    "file": 386199,
    "stage": 0,
    "project": 3318,
    "uid": null,
    "extra": null,
    "context": "雪菜",
    "words": 2
  },
  {
    "id": 111717152,
    "createdAt": "2021-10-18T09:18:52.000Z",
    "updatedAt": null,
    "key": "$PSP_GAME\\USRDIR\\St000\\St109_Cp0002.bin_8",
    "original": "「か、かか、可愛いっ！？\\n　な、何言ってるのよ！　可愛くなんてないわよ！！」",
    "translation": "",
    "file": 386199,
    "stage": 0,
    "project": 3318,
    "uid": null,
    "extra": null,
    "context": "唯",
    "words": 3
  },
  {
    "id": 111717153,
    "createdAt": "2021-10-18T09:18:52.000Z",
    "updatedAt": null,
    "key": "$PSP_GAME\\USRDIR\\St000\\St109_Cp0002.bin_9",
    "original": "「はいはい、わかったからそんなに叫ばないの。\\n　注目集めちゃってるわよ」",
    "translation": "",
    "file": 386199,
    "stage": 0,
    "project": 3318,
    "uid": null,
    "extra": null,
    "context": "雪菜",
    "words": 2
  },
  {
    "id": 111717154,
    "createdAt": "2021-10-18T09:18:52.000Z",
    "updatedAt": null,
    "key": "$PSP_GAME\\USRDIR\\St000\\St109_Cp0002.bin_10",
    "original": "「あ……ご、ごめん……」",
    "translation": "",
    "file": 386199,
    "stage": 0,
    "project": 3318,
    "uid": null,
    "extra": null,
    "context": "唯",
    "words": 1
  },
  {
    "id": 111717155,
    "createdAt": "2021-10-18T09:18:52.000Z",
    "updatedAt": null,
    "key": "$PSP_GAME\\USRDIR\\St000\\St109_Cp0002.bin_11",
    "original": "（い、いけない、稲葉に変なこと言われたからって、\\n　反応しすぎだよね）",
    "translation": "",
    "file": 386199,
    "stage": 0,
    "project": 3318,
    "uid": null,
    "extra": null,
    "context": "",
    "words": 2
  },
  {
    "id": 111717156,
    "createdAt": "2021-10-18T09:18:52.000Z",
    "updatedAt": null,
    "key": "$PSP_GAME\\USRDIR\\St000\\St109_Cp0002.bin_12",
    "original": "（可愛いって雪菜に言われるのはいつものことだし。\\n　そういう意味じゃないに決まってるじゃないの！）",
    "translation": "",
    "file": 386199,
    "stage": 0,
    "project": 3318,
    "uid": null,
    "extra": null,
    "context": "",
    "words": 2
  },
  {
    "id": 111717157,
    "createdAt": "2021-10-18T09:18:52.000Z",
    "updatedAt": null,
    "key": "$PSP_GAME\\USRDIR\\St000\\St109_Cp0002.bin_13",
    "original": "「はぁぁ…………ハッ！　ヤッ！　押忍！\\n　……よし！　もう大丈夫！」",
    "translation": "",
    "file": 386199,
    "stage": 0,
    "project": 3318,
    "uid": null,
    "extra": null,
    "context": "",
    "words": 5
  },
  {
    "id": 111717158,
    "createdAt": "2021-10-18T09:18:52.000Z",
    "updatedAt": null,
    "key": "$PSP_GAME\\USRDIR\\St000\\St109_Cp0002.bin_14",
    "original": "「何が大丈夫なの？」",
    "translation": "",
    "file": 386199,
    "stage": 0,
    "project": 3318,
    "uid": null,
    "extra": null,
    "context": "雪菜",
    "words": 1
  },
  {
    "id": 111717159,
    "createdAt": "2021-10-18T09:18:52.000Z",
    "updatedAt": null,
    "key": "$PSP_GAME\\USRDIR\\St000\\St109_Cp0002.bin_15",
    "original": "「ま、まあ、いいじゃん。\\n　それより早く行かないと遅刻するよ」",
    "translation": "",
    "file": 386199,
    "stage": 0,
    "project": 3318,
    "uid": null,
    "extra": null,
    "context": "唯",
    "words": 2
  },
  {
    "id": 111717160,
    "createdAt": "2021-10-18T09:18:52.000Z",
    "updatedAt": null,
    "key": "$PSP_GAME\\USRDIR\\St000\\St109_Cp0002.bin_16",
    "original": "「まだ全然時間あるけど？\\n　まあ、あんたが聞くなって言うならいいけど」",
    "translation": "",
    "file": 386199,
    "stage": 0,
    "project": 3318,
    "uid": null,
    "extra": null,
    "context": "雪菜",
    "words": 2
  },
  {
    "id": 111717161,
    "createdAt": "2021-10-18T09:18:52.000Z",
    "updatedAt": null,
    "key": "$PSP_GAME\\USRDIR\\St000\\St109_Cp0002.bin_17",
    "original": "「う、うん。ありがと雪菜」",
    "translation": "",
    "file": 386199,
    "stage": 0,
    "project": 3318,
    "uid": null,
    "extra": null,
    "context": "唯",
    "words": 1
  },
  {
    "id": 111717162,
    "createdAt": "2021-10-18T09:18:52.000Z",
    "updatedAt": null,
    "key": "$PSP_GAME\\USRDIR\\St000\\St109_Cp0002.bin_18",
    "original": "「そこで礼を言うってことは、\\n　何か悩んでることがあるみたいね？」",
    "translation": "",
    "file": 386199,
    "stage": 0,
    "project": 3318,
    "uid": null,
    "extra": null,
    "context": "雪菜",
    "words": 2
  },
  {
    "id": 111717163,
    "createdAt": "2021-10-18T09:18:52.000Z",
    "updatedAt": null,
    "key": "$PSP_GAME\\USRDIR\\St000\\St109_Cp0002.bin_19",
    "original": "「ふぇっ！？　な、ないっ！　ないから！」",
    "translation": "",
    "file": 386199,
    "stage": 0,
    "project": 3318,
    "uid": null,
    "extra": null,
    "context": "唯",
    "words": 3
  },
  {
    "id": 111717164,
    "createdAt": "2021-10-18T09:18:52.000Z",
    "updatedAt": null,
    "key": "$PSP_GAME\\USRDIR\\St000\\St109_Cp0002.bin_20",
    "original": "「はいはい。聞かないであげるから、\\n　ちょっとコンビニまで付き合いなさいよ」",
    "translation": "",
    "file": 386199,
    "stage": 0,
    "project": 3318,
    "uid": null,
    "extra": null,
    "context": "雪菜",
    "words": 2
  },
  {
    "id": 111717165,
    "createdAt": "2021-10-18T09:18:52.000Z",
    "updatedAt": null,
    "key": "$PSP_GAME\\USRDIR\\St000\\St109_Cp0002.bin_21",
    "original": "「え？　コンビニ？」",
    "translation": "",
    "file": 386199,
    "stage": 0,
    "project": 3318,
    "uid": null,
    "extra": null,
    "context": "唯",
    "words": 2
  },
  {
    "id": 111717166,
    "createdAt": "2021-10-18T09:18:52.000Z",
    "updatedAt": null,
    "key": "$PSP_GAME\\USRDIR\\St000\\St109_Cp0002.bin_22",
    "original": "「うん。朝ご飯食べたんだけど、まだお腹すいてるの。\\n　肉まんでも食べない？」",
    "translation": "",
    "file": 386199,
    "stage": 0,
    "project": 3318,
    "uid": null,
    "extra": null,
    "context": "雪菜",
    "words": 2
  },
  {
    "id": 111717167,
    "createdAt": "2021-10-18T09:18:52.000Z",
    "updatedAt": null,
    "key": "$PSP_GAME\\USRDIR\\St000\\St109_Cp0002.bin_23",
    "original": "「い、いい。いい！　あたしはお腹すいてないし」",
    "translation": "",
    "file": 386199,
    "stage": 0,
    "project": 3318,
    "uid": null,
    "extra": null,
    "context": "唯",
    "words": 2
  },
  {
    "id": 111717168,
    "createdAt": "2021-10-18T09:18:52.000Z",
    "updatedAt": null,
    "key": "$PSP_GAME\\USRDIR\\St000\\St109_Cp0002.bin_24",
    "original": "（それに、今日は出来るだけ雪菜と２人きりになるのは\\n　避けたいし……）",
    "translation": "",
    "file": 386199,
    "stage": 0,
    "project": 3318,
    "uid": null,
    "extra": null,
    "context": "",
    "words": 2
  },
  {
    "id": 111717169,
    "createdAt": "2021-10-18T09:18:52.000Z",
    "updatedAt": null,
    "key": "$PSP_GAME\\USRDIR\\St000\\St109_Cp0002.bin_25",
    "original": "「えー、１人で買い食いって恥ずかしいじゃん。\\n　奢るから付き合ってよー」",
    "translation": "",
    "file": 386199,
    "stage": 0,
    "project": 3318,
    "uid": null,
    "extra": null,
    "context": "雪菜",
    "words": 2
  },
  {
    "id": 111717170,
    "createdAt": "2021-10-18T09:18:52.000Z",
    "updatedAt": null,
    "key": "$PSP_GAME\\USRDIR\\St000\\St109_Cp0002.bin_26",
    "original": "「う、うーん……」",
    "translation": "",
    "file": 386199,
    "stage": 0,
    "project": 3318,
    "uid": null,
    "extra": null,
    "context": "唯",
    "words": 1
  },
  {
    "id": 111717171,
    "createdAt": "2021-10-18T09:18:52.000Z",
    "updatedAt": null,
    "key": "$PSP_GAME\\USRDIR\\St000\\St109_Cp0002.bin_27",
    "original": "「なによ、あたしの肉まんが食べられないっていうの？」",
    "translation": "",
    "file": 386199,
    "stage": 0,
    "project": 3318,
    "uid": null,
    "extra": null,
    "context": "雪菜",
    "words": 1
  },
  {
    "id": 111717172,
    "createdAt": "2021-10-18T09:18:52.000Z",
    "updatedAt": null,
    "key": "$PSP_GAME\\USRDIR\\St000\\St109_Cp0002.bin_28",
    "original": "「どこの酔っ払いよ！\\n　もう、わかったわよ。付き合うわよ」",
    "translation": "",
    "file": 386199,
    "stage": 0,
    "project": 3318,
    "uid": null,
    "extra": null,
    "context": "唯",
    "words": 2
  },
  {
    "id": 111717173,
    "createdAt": "2021-10-18T09:18:52.000Z",
    "updatedAt": null,
    "key": "$PSP_GAME\\USRDIR\\St000\\St109_Cp0002.bin_29",
    "original": "「やった！　じゃ、行こう！」",
    "translation": "",
    "file": 386199,
    "stage": 0,
    "project": 3318,
    "uid": null,
    "extra": null,
    "context": "雪菜",
    "words": 2
  },
  {
    "id": 111717174,
    "createdAt": "2021-10-18T09:18:52.000Z",
    "updatedAt": null,
    "key": "$PSP_GAME\\USRDIR\\St000\\St109_Cp0002.bin_30",
    "original": "（２人きりになるのは避けたいけど、\\n　あんまり避けすぎるのも悪いしね。\\n　ま、肉まん食べるだけなら大丈夫でしょ）",
    "translation": "",
    "file": 386199,
    "stage": 0,
    "project": 3318,
    "uid": null,
    "extra": null,
    "context": "唯",
    "words": 3
  },
  {
    "id": 111717175,
    "createdAt": "2021-10-18T09:18:52.000Z",
    "updatedAt": null,
    "key": "$PSP_GAME\\USRDIR\\St000\\St109_Cp0002.bin_31",
    "original": "「いっただっきまーす♪」",
    "translation": "",
    "file": 386199,
    "stage": 0,
    "project": 3318,
    "uid": null,
    "extra": null,
    "context": "雪菜",
    "words": 1
  },
  {
    "id": 111717176,
    "createdAt": "2021-10-18T09:18:52.000Z",
    "updatedAt": null,
    "key": "$PSP_GAME\\USRDIR\\St000\\St109_Cp0002.bin_32",
    "original": "「いただきまーす。はむっ」",
    "translation": "",
    "file": 386199,
    "stage": 0,
    "project": 3318,
    "uid": null,
    "extra": null,
    "context": "唯",
    "words": 1
  },
  {
    "id": 111717177,
    "createdAt": "2021-10-18T09:18:52.000Z",
    "updatedAt": null,
    "key": "$PSP_GAME\\USRDIR\\St000\\St109_Cp0002.bin_33",
    "original": "「ん～、美味しいっ！\\n　たまには朝から買い食いもいいよね」",
    "translation": "",
    "file": 386199,
    "stage": 0,
    "project": 3318,
    "uid": null,
    "extra": null,
    "context": "雪菜",
    "words": 2
  },
  {
    "id": 111717178,
    "createdAt": "2021-10-18T09:18:52.000Z",
    "updatedAt": null,
    "key": "$PSP_GAME\\USRDIR\\St000\\St109_Cp0002.bin_34",
    "original": "（雪菜、いつもと変わらないわよね？\\n　あたし、ホントに雪菜と抱き合ったりするのかな？）",
    "translation": "",
    "file": 386199,
    "stage": 0,
    "project": 3318,
    "uid": null,
    "extra": null,
    "context": "唯",
    "words": 2
  }
]